Workbook

Sheet Folha1
S2: Shopping 09/06/2026 | V2: PROMO 09/06/2026
A3: Nomenclatura Amont | B3: Nomenclatura Aval | C3: Grp | D3: GRUPO | E3: FIL | F3: FAM | G3: SFA | H3: ITM8 | I3: DESCRIÇÃO ARTIGO | J3: MARCA | K3: EAN | L3: TIPO | M3: PSYCHO | N3: PROMO PERM (LEADER) | O3: EDLP | P3: Argus | Q3: ST | R3: PVP Cadencier | S3: CONTINENTE | T3: LIDL | U3: PINGO-DOCE | V3: CNT | W3: LIDL | X3: PD | Y3: condição PVP | Z3: _DESVIO % | AA3: _DESVIO € | AB3: check | AC3: Campanha promo futura | AD3: PVP campanha | AE3: NOVO PVP | AF3: Comentarios (face ao suivi) | AG3: HISTORICO | AH3: feedback comercial
A4: g27b053 | B4: r40f34s02 | C4: =MID(A4,2,2) -> 27 | D4: =_xlfn.XLOOKUP(C4,Folha2!A:A,Folha2!B:B) -> TAKE AWAY | E4: =MID(A4,5,3) -> 053 | F4: =MID(B4,5,2) -> 34 | G4: =MID(B4,8,2) -> 02 | H4: 02032022 | I4: GYOZA DE FRANGO 144G | J4: TA TUNG | K4: 8436558315518 | L4: E | M4: N | N4: N | O4: N | P4: N | Q4: 01 | R4: 3.99 | S4: 3.99 | U4: 3.99 | Y4: =IF(OR(N4="O",O4="O"),IF(COUNT(V4:X4)>0,MIN(V4:X4),MIN(S4:U4)),IF(M4="O",MIN(S4:U4),IF(L4="E",IFERROR(MODE(S4:U4),MIN(S4:U4)),AVERAGE(S4:U4)))) -> 3.99 | Z4: =R4/Y4-1 -> 0 | AA4: =R4-Y4 -> 0 | AB4: =R4=Y4 -> TRUE
A5: g27b053 | B5: r40f34s04 | C5: =MID(A5,2,2) -> 27 | D5: =_xlfn.XLOOKUP(C5,Folha2!A:A,Folha2!B:B) -> TAKE AWAY | E5: =MID(A5,5,3) -> 053 | F5: =MID(B5,5,2) -> 34 | G5: =MID(B5,8,2) -> 04 | H5: 02175771 | I5: CHICKENBURGUER 2X135G | J5: M.RANOU | K5: 5604260343614 | L5: MP | M5: O | N5: N | O5: N | P5: O | Q5: 01 | R5: 2.69 | S5: 2.8 | Y5: =IF(OR(N5="O",O5="O"),IF(COUNT(V5:X5)>0,MIN(V5:X5),MIN(S5:U5)),IF(M5="O",MIN(S5:U5),IF(L5="E",IFERROR(MODE(S5:U5),MIN(S5:U5)),AVERAGE(S5:U5)))) -> 2.8 | Z5: =R5/Y5-1 -> -0.039285714 | AA5: =R5-Y5 -> -0.11 | AB5: =R5=Y5 -> FALSE | AC5: 11-06-2026 | AD5: 2.69
A6: g27b053 | B6: r40f34s04 | C6: =MID(A6,2,2) -> 27 | D6: =_xlfn.XLOOKUP(C6,Folha2!A:A,Folha2!B:B) -> TAKE AWAY | E6: =MID(A6,5,3) -> 053 | F6: =MID(B6,5,2) -> 34 | G6: =MID(B6,8,2) -> 04 | H6: 02175782 | I6: CHEESEBURGUER 2X150G | J6: M.RANOU | K6: 5604260343621 | L6: MP | M6: O | N6: N | O6: N | P6: O | Q6: 01 | R6: 2.75 | S6: 2.99 | T6: 2.62 | U6: 2.99 | Y6: =IF(OR(N6="O",O6="O"),IF(COUNT(V6:X6)>0,MIN(V6:X6),MIN(S6:U6)),IF(M6="O",MIN(S6:U6),IF(L6="E",IFERROR(MODE(S6:U6),MIN(S6:U6)),AVERAGE(S6:U6)))) -> 2.62 | Z6: =R6/Y6-1 -> 0.049618321 | AA6: =R6-Y6 -> 0.13 | AB6: =R6=Y6 -> FALSE | AC6: 11-06-2026 | AD6: 2.75
A7: g27b053 | B7: r40f34s04 | C7: =MID(A7,2,2) -> 27 | D7: =_xlfn.XLOOKUP(C7,Folha2!A:A,Folha2!B:B) -> TAKE AWAY | E7: =MID(A7,5,3) -> 053 | F7: =MID(B7,5,2) -> 34 | G7: =MID(B7,8,2) -> 04 | H7: 01942601 | I7: SANDES DELICIAS DO MAR 143G | J7: PORSI | K7: 5604260325788 | L7: MP | M7: N | N7: N | O7: N | P7: N | Q7: 01 | R7: 1.69 | S7: 1.5 | Y7: =IF(OR(N7="O",O7="O"),IF(COUNT(V7:X7)>0,MIN(V7:X7),MIN(S7:U7)),IF(M7="O",MIN(S7:U7),IF(L7="E",IFERROR(MODE(S7:U7),MIN(S7:U7)),AVERAGE(S7:U7)))) -> 1.5 | Z7: =R7/Y7-1 -> 0.12666667 | AA7: =R7-Y7 -> 0.19 | AB7: =R7=Y7 -> FALSE | AC7: 11-06-2026 | AD7: 1.69
A8: g27b053 | B8: r40f34s04 | C8: =MID(A8,2,2) -> 27 | D8: =_xlfn.XLOOKUP(C8,Folha2!A:A,Folha2!B:B) -> TAKE AWAY | E8: =MID(A8,5,3) -> 053 | F8: =MID(B8,5,2) -> 34 | G8: =MID(B8,8,2) -> 04 | H8: 01942623 | I8: SANDES MISTA 200G | J8: PORSI | K8: 5604260325771 | L8: MP | M8: N | N8: N | O8: N | P8: N | Q8: 01 | R8: 1.89 | S8: 1.89 | Y8: =IF(OR(N8="O",O8="O"),IF(COUNT(V8:X8)>0,MIN(V8:X8),MIN(S8:U8)),IF(M8="O",MIN(S8:U8),IF(L8="E",IFERROR(MODE(S8:U8),MIN(S8:U8)),AVERAGE(S8:U8)))) -> 1.89 | Z8: =R8/Y8-1 -> 0 | AA8: =R8-Y8 -> 0 | AB8: =R8=Y8 -> TRUE | AC8: 11-06-2026 | AD8: 1.89
A9: g27b053 | B9: r40f34s04 | C9: =MID(A9,2,2) -> 27 | D9: =_xlfn.XLOOKUP(C9,Folha2!A:A,Folha2!B:B) -> TAKE AWAY | E9: =MID(A9,5,3) -> 053 | F9: =MID(B9,5,2) -> 34 | G9: =MID(B9,8,2) -> 04 | H9: 01942612 | I9: SANDES FRANGO 174G | J9: PORSI | K9: 5604260325795 | L9: MP | M9: N | N9: N | O9: N | P9: N | Q9: 01 | R9: 1.99 | S9: 1.88 | Y9: =IF(OR(N9="O",O9="O"),IF(COUNT(V9:X9)>0,MIN(V9:X9),MIN(S9:U9)),IF(M9="O",MIN(S9:U9),IF(L9="E",IFERROR(MODE(S9:U9),MIN(S9:U9)),AVERAGE(S9:U9)))) -> 1.88 | Z9: =R9/Y9-1 -> 0.058510638 | AA9: =R9-Y9 -> 0.11 | AB9: =R9=Y9 -> FALSE | AC9: 11-06-2026 | AD9: 1.99
A10: g27b053 | B10: r40f34s04 | C10: =MID(A10,2,2) -> 27 | D10: =_xlfn.XLOOKUP(C10,Folha2!A:A,Folha2!B:B) -> TAKE AWAY | E10: =MID(A10,5,3) -> 053 | F10: =MID(B10,5,2) -> 34 | G10: =MID(B10,8,2) -> 04 | H10: 01983452 | I10: ROSCA PRES.SERRANO/QUEIJO 420G | J10: PORSI | K10: 5604260328734 | L10: MP | M10: N | N10: N | O10: N | P10: N | Q10: 01 | R10: 3.49 | S10: 3.49 | Y10: =IF(OR(N10="O",O10="O"),IF(COUNT(V10:X10)>0,MIN(V10:X10),MIN(S10:U10)),IF(M10="O",MIN(S10:U10),IF(L10="E",IFERROR(MODE(S10:U10),MIN(S10:U10)),AVERAGE(S10:U10)))) -> 3.49 | Z10: =R10/Y10-1 -> 0 | AA10: =R10-Y10 -> 0 | AB10: =R10=Y10 -> TRUE | AC10: 25-06-2026 | AD10: 3.49
A11: g27b053 | B11: r40f34s06 | C11: =MID(A11,2,2) -> 27 | D11: =_xlfn.XLOOKUP(C11,Folha2!A:A,Folha2!B:B) -> TAKE AWAY | E11: =MID(A11,5,3) -> 053 | F11: =MID(B11,5,2) -> 34 | G11: =MID(B11,8,2) -> 06 | H11: 02175793 | I11: PIZZA FIAMBRE & QUEIJO 360G | J11: CAMPOFRIO | K11: 8410320033503 | L11: E | M11: N | N11: N | O11: N | P11: N | Q11: 01 | R11: 3.99 | S11: 3.99 | Y11: =IF(OR(N11="O",O11="O"),IF(COUNT(V11:X11)>0,MIN(V11:X11),MIN(S11:U11)),IF(M11="O",MIN(S11:U11),IF(L11="E",IFERROR(MODE(S11:U11),MIN(S11:U11)),AVERAGE(S11:U11)))) -> 3.99 | Z11: =R11/Y11-1 -> 0 | AA11: =R11-Y11 -> 0 | AB11: =R11=Y11 -> TRUE | AC11: 04-06-2026 | AD11: 2.99
A12: g27b053 | B12: r40f34s06 | C12: =MID(A12,2,2) -> 27 | D12: =_xlfn.XLOOKUP(C12,Folha2!A:A,Folha2!B:B) -> TAKE AWAY | E12: =MID(A12,5,3) -> 053 | F12: =MID(B12,5,2) -> 34 | G12: =MID(B12,8,2) -> 06 | H12: 02175802 | I12: PIZZA BARBECUE 410G | J12: CAMPOFRIO | K12: 8410320034319 | L12: E | M12: N | N12: N | O12: N | P12: N | Q12: 01 | R12: 3.99 | S12: 3.99 | Y12: =IF(OR(N12="O",O12="O"),IF(COUNT(V12:X12)>0,MIN(V12:X12),MIN(S12:U12)),IF(M12="O",MIN(S12:U12),IF(L12="E",IFERROR(MODE(S12:U12),MIN(S12:U12)),AVERAGE(S12:U12)))) -> 3.99 | Z12: =R12/Y12-1 -> 0 | AA12: =R12-Y12 -> 0 | AB12: =R12=Y12 -> TRUE | AC12: 04-06-2026 | AD12: 2.99
A13: g27b053 | B13: r40f34s06 | C13: =MID(A13,2,2) -> 27 | D13: =_xlfn.XLOOKUP(C13,Folha2!A:A,Folha2!B:B) -> TAKE AWAY | E13: =MID(A13,5,3) -> 053 | F13: =MID(B13,5,2) -> 34 | G13: =MID(B13,8,2) -> 06 | H13: 02175813 | I13: PIZZA CARBONARA 360G | J13: CAMPOFRIO | K13: 8410320133692 | L13: E | M13: N | N13: N | O13: N | P13: N | Q13: 01 | R13: 3.99 | S13: 3.99 | Y13: =IF(OR(N13="O",O13="O"),IF(COUNT(V13:X13)>0,MIN(V13:X13),MIN(S13:U13)),IF(M13="O",MIN(S13:U13),IF(L13="E",IFERROR(MODE(S13:U13),MIN(S13:U13)),AVERAGE(S13:U13)))) -> 3.99 | Z13: =R13/Y13-1 -> 0 | AA13: =R13-Y13 -> 0 | AB13: =R13=Y13 -> TRUE | AC13: 04-06-2026 | AD13: 2.99
A14: g27b053 | B14: r40f34s06 | C14: =MID(A14,2,2) -> 27 | D14: =_xlfn.XLOOKUP(C14,Folha2!A:A,Folha2!B:B) -> TAKE AWAY | E14: =MID(A14,5,3) -> 053 | F14: =MID(B14,5,2) -> 34 | G14: =MID(B14,8,2) -> 06 | H14: 02038800 | I14: PIZZA ROMANA 410G | J14: PORSI | K14: 5604260331437 | L14: MP | M14: O | N14: N | O14: N | P14: O | Q14: 01 | R14: 2.69 | S14: 2.66 | T14: 2.56 | U14: 2.66 | Y14: =IF(OR(N14="O",O14="O"),IF(COUNT(V14:X14)>0,MIN(V14:X14),MIN(S14:U14)),IF(M14="O",MIN(S14:U14),IF(L14="E",IFERROR(MODE(S14:U14),MIN(S14:U14)),AVERAGE(S14:U14)))) -> 2.56 | Z14: =R14/Y14-1 -> 0.05078125 | AA14: =R14-Y14 -> 0.13 | AB14: =R14=Y14 -> FALSE | AC14: 11-06-2026 | AD14: 2.69
A15: g27b053 | B15: r40f34s06 | C15: =MID(A15,2,2) -> 27 | D15: =_xlfn.XLOOKUP(C15,Folha2!A:A,Folha2!B:B) -> TAKE AWAY | E15: =MID(A15,5,3) -> 053 | F15: =MID(B15,5,2) -> 34 | G15: =MID(B15,8,2) -> 06 | H15: 02038791 | I15: PIZZA FIAMBRE E QUEIJO 410G | J15: PORSI | K15: 5604260331420 | L15: MP | M15: O | N15: N | O15: N | P15: O | Q15: 01 | R15: 2.69 | S15: 2.69 | T15: 2.66 | U15: 2.69 | Y15: =IF(OR(N15="O",O15="O"),IF(COUNT(V15:X15)>0,MIN(V15:X15),MIN(S15:U15)),IF(M15="O",MIN(S15:U15),IF(L15="E",IFERROR(MODE(S15:U15),MIN(S15:U15)),AVERAGE(S15:U15)))) -> 2.66 | Z15: =R15/Y15-1 -> 0.011278195 | AA15: =R15-Y15 -> 0.03 | AB15: =R15=Y15 -> FALSE | AC15: 11-06-2026 | AD15: 2.69
A16: g27b053 | B16: r40f34s06 | C16: =MID(A16,2,2) -> 27 | D16: =_xlfn.XLOOKUP(C16,Folha2!A:A,Folha2!B:B) -> TAKE AWAY | E16: =MID(A16,5,3) -> 053 | F16: =MID(B16,5,2) -> 34 | G16: =MID(B16,8,2) -> 06 | H16: 02038776 | I16: PIZZA 4 QUEIJOS 380G | J16: PORSI | K16: 5604260331406 | L16: MP | M16: O | N16: N | O16: N | P16: O | Q16: 01 | R16: 2.75 | S16: 2.75 | T16: 2.68 | U16: 2.82 | Y16: =IF(OR(N16="O",O16="O"),IF(COUNT(V16:X16)>0,MIN(V16:X16),MIN(S16:U16)),IF(M16="O",MIN(S16:U16),IF(L16="E",IFERROR(MODE(S16:U16),MIN(S16:U16)),AVERAGE(S16:U16)))) -> 2.68 | Z16: =R16/Y16-1 -> 0.026119403 | AA16: =R16-Y16 -> 0.07 | AB16: =R16=Y16 -> FALSE | AC16: 11-06-2026 | AD16: 2.75
A17: g27b053 | B17: r40f34s06 | C17: =MID(A17,2,2) -> 27 | D17: =_xlfn.XLOOKUP(C17,Folha2!A:A,Folha2!B:B) -> TAKE AWAY | E17: =MID(A17,5,3) -> 053 | F17: =MID(B17,5,2) -> 34 | G17: =MID(B17,8,2) -> 06 | H17: 02038765 | I17: PIZZA CARBONARA 415G | J17: PORSI | K17: 5604260331390 | L17: MP | M17: O | N17: N | O17: N | P17: O | Q17: 01 | R17: 2.89 | S17: 2.93 | T17: 2.79 | U17: 2.89 | Y17: =IF(OR(N17="O",O17="O"),IF(COUNT(V17:X17)>0,MIN(V17:X17),MIN(S17:U17)),IF(M17="O",MIN(S17:U17),IF(L17="E",IFERROR(MODE(S17:U17),MIN(S17:U17)),AVERAGE(S17:U17)))) -> 2.79 | Z17: =R17/Y17-1 -> 0.035842294 | AA17: =R17-Y17 -> 0.1 | AB17: =R17=Y17 -> FALSE | AC17: 11-06-2026 | AD17: 2.89
A18: g27b053 | B18: r40f34s06 | C18: =MID(A18,2,2) -> 27 | D18: =_xlfn.XLOOKUP(C18,Folha2!A:A,Folha2!B:B) -> TAKE AWAY | E18: =MID(A18,5,3) -> 053 | F18: =MID(B18,5,2) -> 34 | G18: =MID(B18,8,2) -> 06 | H18: 02038780 | I18: PIZZA ATUM E BACON 410G | J18: PORSI | K18: 5604260331413 | L18: MP | M18: O | N18: N | O18: N | P18: O | Q18: 01 | R18: 2.95 | S18: 2.96 | T18: 2.86 | U18: 2.93 | Y18: =IF(OR(N18="O",O18="O"),IF(COUNT(V18:X18)>0,MIN(V18:X18),MIN(S18:U18)),IF(M18="O",MIN(S18:U18),IF(L18="E",IFERROR(MODE(S18:U18),MIN(S18:U18)),AVERAGE(S18:U18)))) -> 2.86 | Z18: =R18/Y18-1 -> 0.031468531 | AA18: =R18-Y18 -> 0.09 | AB18: =R18=Y18 -> FALSE | AC18: 11-06-2026 | AD18: 2.95
A19: g27b053 | B19: r40f34s06 | C19: =MID(A19,2,2) -> 27 | D19: =_xlfn.XLOOKUP(C19,Folha2!A:A,Folha2!B:B) -> TAKE AWAY | E19: =MID(A19,5,3) -> 053 | F19: =MID(B19,5,2) -> 34 | G19: =MID(B19,8,2) -> 06 | H19: 02038811 | I19: PIZZA BARBECUE 410G | J19: PORSI | K19: 5604260331444 | L19: MP | M19: O | N19: N | O19: N | P19: O | Q19: 01 | R19: 2.99 | S19: 2.96 | T19: 2.86 | Y19: =IF(OR(N19="O",O19="O"),IF(COUNT(V19:X19)>0,MIN(V19:X19),MIN(S19:U19)),IF(M19="O",MIN(S19:U19),IF(L19="E",IFERROR(MODE(S19:U19),MIN(S19:U19)),AVERAGE(S19:U19)))) -> 2.86 | Z19: =R19/Y19-1 -> 0.045454545 | AA19: =R19-Y19 -> 0.13 | AB19: =R19=Y19 -> FALSE | AC19: 11-06-2026 | AD19: 2.99
A20: g27b053 | B20: r40f34s10 | C20: =MID(A20,2,2) -> 27 | D20: =_xlfn.XLOOKUP(C20,Folha2!A:A,Folha2!B:B) -> TAKE AWAY | E20: =MID(A20,5,3) -> 053 | F20: =MID(B20,5,2) -> 34 | G20: =MID(B20,8,2) -> 10 | H20: 01647535 | I20: GASPACHO ORIGINAL 1L | J20: ALVALLE | K20: 8422174010029 | L20: E | M20: N | N20: N | O20: N | P20: N | Q20: 01 | R20: 4.49 | S20: 4.49 | V20: 2.24 | Y20: =IF(OR(N20="O",O20="O"),IF(COUNT(V20:X20)>0,MIN(V20:X20),MIN(S20:U20)),IF(M20="O",MIN(S20:U20),IF(L20="E",IFERROR(MODE(S20:U20),MIN(S20:U20)),AVERAGE(S20:U20)))) -> 4.49 | Z20: =R20/Y20-1 -> 0 | AA20: =R20-Y20 -> 0 | AB20: =R20=Y20 -> TRUE | AC20: 09-07-2026 | AD20: 2.89
A21: g27b053 | B21: r40f34s10 | C21: =MID(A21,2,2) -> 27 | D21: =_xlfn.XLOOKUP(C21,Folha2!A:A,Folha2!B:B) -> TAKE AWAY | E21: =MID(A21,5,3) -> 053 | F21: =MID(B21,5,2) -> 34 | G21: =MID(B21,8,2) -> 10 | H21: 01754795 | I21: CREME DE CENOURA 400G | J21: PORSI | K21: 5604260298181 | L21: MP | M21: N | N21: N | O21: N | P21: N | Q21: 01 | R21: 1.39 | S21: 1.59 | T21: 1.39 | U21: 1.59 | Y21: =IF(OR(N21="O",O21="O"),IF(COUNT(V21:X21)>0,MIN(V21:X21),MIN(S21:U21)),IF(M21="O",MIN(S21:U21),IF(L21="E",IFERROR(MODE(S21:U21),MIN(S21:U21)),AVERAGE(S21:U21)))) -> 1.5233333 | Z21: =R21/Y21-1 -> -0.087527352 | AA21: =R21-Y21 -> -0.13333333 | AB21: =R21=Y21 -> FALSE | AC21: 02-07-2026 | AD21: 1.39
A22: g27b053 | B22: r40f34s10 | C22: =MID(A22,2,2) -> 27 | D22: =_xlfn.XLOOKUP(C22,Folha2!A:A,Folha2!B:B) -> TAKE AWAY | E22: =MID(A22,5,3) -> 053 | F22: =MID(B22,5,2) -> 34 | G22: =MID(B22,8,2) -> 10 | H22: 01754784 | I22: SOPA LEGUMES 400G | J22: PORSI | K22: 5604260298174 | L22: MP | M22: N | N22: N | O22: N | P22: N | Q22: 01 | R22: 1.39 | S22: 1.79 | T22: 1.39 | Y22: =IF(OR(N22="O",O22="O"),IF(COUNT(V22:X22)>0,MIN(V22:X22),MIN(S22:U22)),IF(M22="O",MIN(S22:U22),IF(L22="E",IFERROR(MODE(S22:U22),MIN(S22:U22)),AVERAGE(S22:U22)))) -> 1.59 | Z22: =R22/Y22-1 -> -0.12578616 | AA22: =R22-Y22 -> -0.2 | AB22: =R22=Y22 -> FALSE | AC22: 11-06-2026 | AD22: 1.39
A23: g27b053 | B23: r40f34s10 | C23: =MID(A23,2,2) -> 27 | D23: =_xlfn.XLOOKUP(C23,Folha2!A:A,Folha2!B:B) -> TAKE AWAY | E23: =MID(A23,5,3) -> 053 | F23: =MID(B23,5,2) -> 34 | G23: =MID(B23,8,2) -> 10 | H23: 02106296 | I23: CALDO VERDE C/CHOURICO 400G | J23: PORSI | K23: 5604260332021 | L23: MP | M23: N | N23: N | O23: N | P23: N | Q23: 01 | R23: 1.69 | S23: 1.59 | Y23: =IF(OR(N23="O",O23="O"),IF(COUNT(V23:X23)>0,MIN(V23:X23),MIN(S23:U23)),IF(M23="O",MIN(S23:U23),IF(L23="E",IFERROR(MODE(S23:U23),MIN(S23:U23)),AVERAGE(S23:U23)))) -> 1.59 | Z23: =R23/Y23-1 -> 0.062893082 | AA23: =R23-Y23 -> 0.1 | AB23: =R23=Y23 -> FALSE
A24: g27b053 | B24: r40f34s10 | C24: =MID(A24,2,2) -> 27 | D24: =_xlfn.XLOOKUP(C24,Folha2!A:A,Folha2!B:B) -> TAKE AWAY | E24: =MID(A24,5,3) -> 053 | F24: =MID(B24,5,2) -> 34 | G24: =MID(B24,8,2) -> 10 | H24: 01851894 | I24: SOPA DE AGRIAO 400G | J24: PORSI | K24: 5604260310098 | L24: MP | M24: N | N24: N | O24: N | P24: N | Q24: 01 | R24: 1.89 | S24: 1.69 | Y24: =IF(OR(N24="O",O24="O"),IF(COUNT(V24:X24)>0,MIN(V24:X24),MIN(S24:U24)),IF(M24="O",MIN(S24:U24),IF(L24="E",IFERROR(MODE(S24:U24),MIN(S24:U24)),AVERAGE(S24:U24)))) -> 1.69 | Z24: =R24/Y24-1 -> 0.1183432 | AA24: =R24-Y24 -> 0.2 | AB24: =R24=Y24 -> FALSE | AC24: 11-06-2026 | AD24: 1.89
A25: g27b053 | B25: r40f34s10 | C25: =MID(A25,2,2) -> 27 | D25: =_xlfn.XLOOKUP(C25,Folha2!A:A,Folha2!B:B) -> TAKE AWAY | E25: =MID(A25,5,3) -> 053 | F25: =MID(B25,5,2) -> 34 | G25: =MID(B25,8,2) -> 10 | H25: 01981345 | I25: SOPA DE FEIJAO VERDE 400G | J25: PORSI | K25: 5604260328536 | L25: MP | M25: N | N25: N | O25: N | P25: N | Q25: 01 | R25: 1.89 | S25: 1.79 | Y25: =IF(OR(N25="O",O25="O"),IF(COUNT(V25:X25)>0,MIN(V25:X25),MIN(S25:U25)),IF(M25="O",MIN(S25:U25),IF(L25="E",IFERROR(MODE(S25:U25),MIN(S25:U25)),AVERAGE(S25:U25)))) -> 1.79 | Z25: =R25/Y25-1 -> 0.055865922 | AA25: =R25-Y25 -> 0.1 | AB25: =R25=Y25 -> FALSE | AC25: 11-06-2026 | AD25: 1.89
A26: g27b053 | B26: r40f34s10 | C26: =MID(A26,2,2) -> 27 | D26: =_xlfn.XLOOKUP(C26,Folha2!A:A,Folha2!B:B) -> TAKE AWAY | E26: =MID(A26,5,3) -> 053 | F26: =MID(B26,5,2) -> 34 | G26: =MID(B26,8,2) -> 10 | H26: 02106305 | I26: SOPA CAMPONESA 400G | J26: PORSI | K26: 5604260335428 | L26: MP | M26: N | N26: N | O26: N | P26: N | Q26: 01 | R26: 1.89 | S26: 1.79 | Y26: =IF(OR(N26="O",O26="O"),IF(COUNT(V26:X26)>0,MIN(V26:X26),MIN(S26:U26)),IF(M26="O",MIN(S26:U26),IF(L26="E",IFERROR(MODE(S26:U26),MIN(S26:U26)),AVERAGE(S26:U26)))) -> 1.79 | Z26: =R26/Y26-1 -> 0.055865922 | AA26: =R26-Y26 -> 0.1 | AB26: =R26=Y26 -> FALSE | AC26: 11-06-2026 | AD26: 1.89
A27: g27b053 | B27: r40f34s10 | C27: =MID(A27,2,2) -> 27 | D27: =_xlfn.XLOOKUP(C27,Folha2!A:A,Folha2!B:B) -> TAKE AWAY | E27: =MID(A27,5,3) -> 053 | F27: =MID(B27,5,2) -> 34 | G27: =MID(B27,8,2) -> 10 | H27: 01794261 | I27: GASPACHO 1L | J27: PORSI | K27: 5604260301478 | L27: MP | M27: N | N27: N | O27: N | P27: N | Q27: 01 | R27: 2.09 | S27: 1.89 | U27: 1.89 | Y27: =IF(OR(N27="O",O27="O"),IF(COUNT(V27:X27)>0,MIN(V27:X27),MIN(S27:U27)),IF(M27="O",MIN(S27:U27),IF(L27="E",IFERROR(MODE(S27:U27),MIN(S27:U27)),AVERAGE(S27:U27)))) -> 1.89 | Z27: =R27/Y27-1 -> 0.10582011 | AA27: =R27-Y27 -> 0.2 | AB27: =R27=Y27 -> FALSE
A28: g27b053 | B28: r40f34s10 | C28: =MID(A28,2,2) -> 27 | D28: =_xlfn.XLOOKUP(C28,Folha2!A:A,Folha2!B:B) -> TAKE AWAY | E28: =MID(A28,5,3) -> 053 | F28: =MID(B28,5,2) -> 34 | G28: =MID(B28,8,2) -> 10 | H28: 01932962 | I28: SOPA DE LEGUMES 800G | J28: PORSI | K28: 5604260320561 | L28: MP | M28: O | N28: N | O28: N | P28: O | Q28: 01 | R28: 2.49 | S28: 2.49 | U28: 2.48 | Y28: =IF(OR(N28="O",O28="O"),IF(COUNT(V28:X28)>0,MIN(V28:X28),MIN(S28:U28)),IF(M28="O",MIN(S28:U28),IF(L28="E",IFERROR(MODE(S28:U28),MIN(S28:U28)),AVERAGE(S28:U28)))) -> 2.48 | Z28: =R28/Y28-1 -> 0.0040322581 | AA28: =R28-Y28 -> 0.01 | AB28: =R28=Y28 -> FALSE | AC28: 04-06-2026 | AD28: 1.99
A29: g27b053 | B29: r40f34s10 | C29: =MID(A29,2,2) -> 27 | D29: =_xlfn.XLOOKUP(C29,Folha2!A:A,Folha2!B:B) -> TAKE AWAY | E29: =MID(A29,5,3) -> 053 | F29: =MID(B29,5,2) -> 34 | G29: =MID(B29,8,2) -> 10 | H29: 01932951 | I29: CREME DE CENOURA 800G | J29: PORSI | K29: 5604260320578 | L29: MP | M29: O | N29: N | O29: N | P29: O | Q29: 01 | R29: 2.69 | S29: 2.49 | Y29: =IF(OR(N29="O",O29="O"),IF(COUNT(V29:X29)>0,MIN(V29:X29),MIN(S29:U29)),IF(M29="O",MIN(S29:U29),IF(L29="E",IFERROR(MODE(S29:U29),MIN(S29:U29)),AVERAGE(S29:U29)))) -> 2.49 | Z29: =R29/Y29-1 -> 0.080321285 | AA29: =R29-Y29 -> 0.2 | AB29: =R29=Y29 -> FALSE | AC29: 04-06-2026 | AD29: 1.99
A30: g27b053 | B30: r40f34s10 | C30: =MID(A30,2,2) -> 27 | D30: =_xlfn.XLOOKUP(C30,Folha2!A:A,Folha2!B:B) -> TAKE AWAY | E30: =MID(A30,5,3) -> 053 | F30: =MID(B30,5,2) -> 34 | G30: =MID(B30,8,2) -> 10 | H30: 01932973 | I30: SOPA DE AGRIAO 800G | J30: PORSI | K30: 5604260323197 | L30: MP | M30: O | N30: N | O30: N | P30: O | Q30: 01 | R30: 2.69 | S30: 2.49 | Y30: =IF(OR(N30="O",O30="O"),IF(COUNT(V30:X30)>0,MIN(V30:X30),MIN(S30:U30)),IF(M30="O",MIN(S30:U30),IF(L30="E",IFERROR(MODE(S30:U30),MIN(S30:U30)),AVERAGE(S30:U30)))) -> 2.49 | Z30: =R30/Y30-1 -> 0.080321285 | AA30: =R30-Y30 -> 0.2 | AB30: =R30=Y30 -> FALSE | AC30: 04-06-2026 | AD30: 1.99
A31: g27b053 | B31: r40f34s12 | C31: =MID(A31,2,2) -> 27 | D31: =_xlfn.XLOOKUP(C31,Folha2!A:A,Folha2!B:B) -> TAKE AWAY | E31: =MID(A31,5,3) -> 053 | F31: =MID(B31,5,2) -> 34 | G31: =MID(B31,8,2) -> 12 | H31: 01856021 | I31: MASSA CARBONARA 300G | J31: PORSI | K31: 5604260309917 | L31: MP | M31: N | N31: N | O31: N | P31: N | Q31: 01 | R31: 2.99 | S31: 2.99 | T31: 2.36 | Y31: =IF(OR(N31="O",O31="O"),IF(COUNT(V31:X31)>0,MIN(V31:X31),MIN(S31:U31)),IF(M31="O",MIN(S31:U31),IF(L31="E",IFERROR(MODE(S31:U31),MIN(S31:U31)),AVERAGE(S31:U31)))) -> 2.675 | Z31: =R31/Y31-1 -> 0.11775701 | AA31: =R31-Y31 -> 0.315 | AB31: =R31=Y31 -> FALSE
A32: g27b053 | B32: r40f34s12 | C32: =MID(A32,2,2) -> 27 | D32: =_xlfn.XLOOKUP(C32,Folha2!A:A,Folha2!B:B) -> TAKE AWAY | E32: =MID(A32,5,3) -> 053 | F32: =MID(B32,5,2) -> 34 | G32: =MID(B32,8,2) -> 12 | H32: 01826725 | I32: ARROZ DE PATO 250G | J32: PORSI | K32: 5604260304066 | L32: MP | M32: N | N32: N | O32: N | P32: N | Q32: 01 | R32: 2.99 | S32: 3.32 | T32: 2.99 | Y32: =IF(OR(N32="O",O32="O"),IF(COUNT(V32:X32)>0,MIN(V32:X32),MIN(S32:U32)),IF(M32="O",MIN(S32:U32),IF(L32="E",IFERROR(MODE(S32:U32),MIN(S32:U32)),AVERAGE(S32:U32)))) -> 3.155 | Z32: =R32/Y32-1 -> -0.05229794 | AA32: =R32-Y32 -> -0.165 | AB32: =R32=Y32 -> FALSE | AC32: 18-06-2026 | AD32: 2.99
A33: g27b053 | B33: r40f34s12 | C33: =MID(A33,2,2) -> 27 | D33: =_xlfn.XLOOKUP(C33,Folha2!A:A,Folha2!B:B) -> TAKE AWAY | E33: =MID(A33,5,3) -> 053 | F33: =MID(B33,5,2) -> 34 | G33: =MID(B33,8,2) -> 12 | H33: 01973960 | I33: CHILLI COM CARNE E ARROZ 350G | J33: PORSI | K33: 5604260328352 | L33: MP | M33: N | N33: N | O33: N | P33: N | Q33: 01 | R33: 3.59 | S33: 3.59 | Y33: =IF(OR(N33="O",O33="O"),IF(COUNT(V33:X33)>0,MIN(V33:X33),MIN(S33:U33)),IF(M33="O",MIN(S33:U33),IF(L33="E",IFERROR(MODE(S33:U33),MIN(S33:U33)),AVERAGE(S33:U33)))) -> 3.59 | Z33: =R33/Y33-1 -> 0 | AA33: =R33-Y33 -> 0 | AB33: =R33=Y33 -> TRUE | AC33: 09-07-2026 | AD33: 3.59
A34: g27b053 | B34: r40f34s12 | C34: =MID(A34,2,2) -> 27 | D34: =_xlfn.XLOOKUP(C34,Folha2!A:A,Folha2!B:B) -> TAKE AWAY | E34: =MID(A34,5,3) -> 053 | F34: =MID(B34,5,2) -> 34 | G34: =MID(B34,8,2) -> 12 | H34: 01826751 | I34: ESPARGUETE BOLONHESA 350G | J34: PORSI | K34: 5604260304097 | L34: MP | M34: N | N34: N | O34: N | P34: N | Q34: 01 | R34: 3.59 | S34: 3.99 | T34: 2.75 | Y34: =IF(OR(N34="O",O34="O"),IF(COUNT(V34:X34)>0,MIN(V34:X34),MIN(S34:U34)),IF(M34="O",MIN(S34:U34),IF(L34="E",IFERROR(MODE(S34:U34),MIN(S34:U34)),AVERAGE(S34:U34)))) -> 3.37 | Z34: =R34/Y34-1 -> 0.065281899 | AA34: =R34-Y34 -> 0.22 | AB34: =R34=Y34 -> FALSE | AC34: 09-07-2026 | AD34: 2.99
A35: g27b053 | B35: r40f34s12 | C35: =MID(A35,2,2) -> 27 | D35: =_xlfn.XLOOKUP(C35,Folha2!A:A,Folha2!B:B) -> TAKE AWAY | E35: =MID(A35,5,3) -> 053 | F35: =MID(B35,5,2) -> 34 | G35: =MID(B35,8,2) -> 12 | H35: 01973971 | I35: EMPADAO CARNE GRATINADO 350G | J35: PORSI | K35: 5604260327607 | L35: MP | M35: N | N35: N | O35: N | P35: N | Q35: 01 | R35: 3.99 | S35: 4.02 | Y35: =IF(OR(N35="O",O35="O"),IF(COUNT(V35:X35)>0,MIN(V35:X35),MIN(S35:U35)),IF(M35="O",MIN(S35:U35),IF(L35="E",IFERROR(MODE(S35:U35),MIN(S35:U35)),AVERAGE(S35:U35)))) -> 4.02 | Z35: =R35/Y35-1 -> -0.0074626866 | AA35: =R35-Y35 -> -0.03 | AB35: =R35=Y35 -> FALSE | AC35: 02-07-2026 | AD35: 3.99
A36: g27b053 | B36: r40f34s12 | C36: =MID(A36,2,2) -> 27 | D36: =_xlfn.XLOOKUP(C36,Folha2!A:A,Folha2!B:B) -> TAKE AWAY | E36: =MID(A36,5,3) -> 053 | F36: =MID(B36,5,2) -> 34 | G36: =MID(B36,8,2) -> 12 | H36: 01973982 | I36: CARIL DE FRANGO 350G | J36: PORSI | K36: 5604260328369 | L36: MP | M36: N | N36: N | O36: N | P36: N | Q36: 01 | R36: 4.69 | S36: 4.66 | Y36: =IF(OR(N36="O",O36="O"),IF(COUNT(V36:X36)>0,MIN(V36:X36),MIN(S36:U36)),IF(M36="O",MIN(S36:U36),IF(L36="E",IFERROR(MODE(S36:U36),MIN(S36:U36)),AVERAGE(S36:U36)))) -> 4.66 | Z36: =R36/Y36-1 -> 0.0064377682 | AA36: =R36-Y36 -> 0.03 | AB36: =R36=Y36 -> FALSE
A37: g27b053 | B37: r40f34s12 | C37: =MID(A37,2,2) -> 27 | D37: =_xlfn.XLOOKUP(C37,Folha2!A:A,Folha2!B:B) -> TAKE AWAY | E37: =MID(A37,5,3) -> 053 | F37: =MID(B37,5,2) -> 34 | G37: =MID(B37,8,2) -> 12 | H37: 01912133 | I37: FRANCESINHA 500G | J37: PORSI | K37: 5604260309900 | L37: MP | M37: N | N37: N | O37: N | P37: N | Q37: 01 | R37: 6.49 | S37: 6.49 | T37: 6.49 | Y37: =IF(OR(N37="O",O37="O"),IF(COUNT(V37:X37)>0,MIN(V37:X37),MIN(S37:U37)),IF(M37="O",MIN(S37:U37),IF(L37="E",IFERROR(MODE(S37:U37),MIN(S37:U37)),AVERAGE(S37:U37)))) -> 6.49 | Z37: =R37/Y37-1 -> 0 | AA37: =R37-Y37 -> 0 | AB37: =R37=Y37 -> TRUE | AC37: 09-07-2026 | AD37: 6.49
A38: g27b053 | B38: r40f34s12 | C38: =MID(A38,2,2) -> 27 | D38: =_xlfn.XLOOKUP(C38,Folha2!A:A,Folha2!B:B) -> TAKE AWAY | E38: =MID(A38,5,3) -> 053 | F38: =MID(B38,5,2) -> 34 | G38: =MID(B38,8,2) -> 12 | H38: 01813313 | I38: LASANHA A BOLONHESA 350G | J38: RANA | K38: 8001665127684 | L38: E | M38: N | N38: N | O38: N | P38: N | Q38: 01 | R38: 4.49 | S38: 4.49 | U38: 4.49 | Y38: =IF(OR(N38="O",O38="O"),IF(COUNT(V38:X38)>0,MIN(V38:X38),MIN(S38:U38)),IF(M38="O",MIN(S38:U38),IF(L38="E",IFERROR(MODE(S38:U38),MIN(S38:U38)),AVERAGE(S38:U38)))) -> 4.49 | Z38: =R38/Y38-1 -> 0 | AA38: =R38-Y38 -> 0 | AB38: =R38=Y38 -> TRUE | AC38: 23-07-2026 | AD38: 3.34
A39: g27b053 | B39: r40f34s12 | C39: =MID(A39,2,2) -> 27 | D39: =_xlfn.XLOOKUP(C39,Folha2!A:A,Folha2!B:B) -> TAKE AWAY | E39: =MID(A39,5,3) -> 053 | F39: =MID(B39,5,2) -> 34 | G39: =MID(B39,8,2) -> 12 | H39: 02032011 | I39: YAKISOBA COM FRANGO 250G | J39: TA TUNG | K39: 8436558315839 | L39: E | M39: N | N39: N | O39: N | P39: N | Q39: 01 | R39: 4.99 | U39: 4.99 | Y39: =IF(OR(N39="O",O39="O"),IF(COUNT(V39:X39)>0,MIN(V39:X39),MIN(S39:U39)),IF(M39="O",MIN(S39:U39),IF(L39="E",IFERROR(MODE(S39:U39),MIN(S39:U39)),AVERAGE(S39:U39)))) -> 4.99 | Z39: =R39/Y39-1 -> 0 | AA39: =R39-Y39 -> 0 | AB39: =R39=Y39 -> TRUE
A40: g27b053 | B40: r40f34s13 | C40: =MID(A40,2,2) -> 27 | D40: =_xlfn.XLOOKUP(C40,Folha2!A:A,Folha2!B:B) -> TAKE AWAY | E40: =MID(A40,5,3) -> 053 | F40: =MID(B40,5,2) -> 34 | G40: =MID(B40,8,2) -> 13 | H40: 01826736 | I40: BACALHAU COM NATAS 250G | J40: PORSI | K40: 5604260304073 | L40: MP | M40: N | N40: N | O40: N | P40: N | Q40: 01 | R40: 3.29 | S40: 3.32 | Y40: =IF(OR(N40="O",O40="O"),IF(COUNT(V40:X40)>0,MIN(V40:X40),MIN(S40:U40)),IF(M40="O",MIN(S40:U40),IF(L40="E",IFERROR(MODE(S40:U40),MIN(S40:U40)),AVERAGE(S40:U40)))) -> 3.32 | Z40: =R40/Y40-1 -> -0.0090361446 | AA40: =R40-Y40 -> -0.03 | AB40: =R40=Y40 -> FALSE
A41: g27b053 | B41: r40f34s13 | C41: =MID(A41,2,2) -> 27 | D41: =_xlfn.XLOOKUP(C41,Folha2!A:A,Folha2!B:B) -> TAKE AWAY | E41: =MID(A41,5,3) -> 053 | F41: =MID(B41,5,2) -> 34 | G41: =MID(B41,8,2) -> 13 | H41: 01856010 | I41: BACALHAU A BRAS 250G | J41: PORSI | K41: 5604260309894 | L41: MP | M41: N | N41: N | O41: N | P41: N | Q41: 01 | R41: 3.99 | S41: 3.99 | Y41: =IF(OR(N41="O",O41="O"),IF(COUNT(V41:X41)>0,MIN(V41:X41),MIN(S41:U41)),IF(M41="O",MIN(S41:U41),IF(L41="E",IFERROR(MODE(S41:U41),MIN(S41:U41)),AVERAGE(S41:U41)))) -> 3.99 | Z41: =R41/Y41-1 -> 0 | AA41: =R41-Y41 -> 0 | AB41: =R41=Y41 -> TRUE | AC41: 09-07-2026 | AD41: 3.99
A42: g27b053 | B42: r40f34s13 | C42: =MID(A42,2,2) -> 27 | D42: =_xlfn.XLOOKUP(C42,Folha2!A:A,Folha2!B:B) -> TAKE AWAY | E42: =MID(A42,5,3) -> 053 | F42: =MID(B42,5,2) -> 34 | G42: =MID(B42,8,2) -> 13 | H42: 01856006 | I42: ACORDA DE CAMARAO 300G | J42: PORSI | K42: 5604260309887 | L42: MP | M42: N | N42: N | O42: N | P42: N | Q42: 01 | R42: 4.29 | S42: 4.29 | Y42: =IF(OR(N42="O",O42="O"),IF(COUNT(V42:X42)>0,MIN(V42:X42),MIN(S42:U42)),IF(M42="O",MIN(S42:U42),IF(L42="E",IFERROR(MODE(S42:U42),MIN(S42:U42)),AVERAGE(S42:U42)))) -> 4.29 | Z42: =R42/Y42-1 -> 0 | AA42: =R42-Y42 -> 0 | AB42: =R42=Y42 -> TRUE | AC42: 02-07-2026 | AD42: 4.29
A43: g27b053 | B43: r40f34s13 | C43: =MID(A43,2,2) -> 27 | D43: =_xlfn.XLOOKUP(C43,Folha2!A:A,Folha2!B:B) -> TAKE AWAY | E43: =MID(A43,5,3) -> 053 | F43: =MID(B43,5,2) -> 34 | G43: =MID(B43,8,2) -> 13 | H43: 01826740 | I43: BACALHAU COM NATAS 800G | J43: PORSI | K43: 5604260304080 | L43: MP | M43: N | N43: N | O43: N | P43: N | Q43: 01 | R43: 9.99 | S43: 10.27 | U43: 11.42 | Y43: =IF(OR(N43="O",O43="O"),IF(COUNT(V43:X43)>0,MIN(V43:X43),MIN(S43:U43)),IF(M43="O",MIN(S43:U43),IF(L43="E",IFERROR(MODE(S43:U43),MIN(S43:U43)),AVERAGE(S43:U43)))) -> 10.845 | Z43: =R43/Y43-1 -> -0.078838174 | AA43: =R43-Y43 -> -0.855 | AB43: =R43=Y43 -> FALSE | AC43: 25-06-2026 | AD43: 8.99
A44: g27b053 | B44: r40f34s14 | C44: =MID(A44,2,2) -> 27 | D44: =_xlfn.XLOOKUP(C44,Folha2!A:A,Folha2!B:B) -> TAKE AWAY | E44: =MID(A44,5,3) -> 053 | F44: =MID(B44,5,2) -> 34 | G44: =MID(B44,8,2) -> 14 | H44: 01875823 | I44: HAMBURGUER VEGETARIANO 150G | J44: G.GOURMET | K44: 8445291919464 | L44: E | M44: N | N44: N | O44: N | P44: N | Q44: 07 | R44: 3.59 | S44: 3.59 | Y44: =IF(OR(N44="O",O44="O"),IF(COUNT(V44:X44)>0,MIN(V44:X44),MIN(S44:U44)),IF(M44="O",MIN(S44:U44),IF(L44="E",IFERROR(MODE(S44:U44),MIN(S44:U44)),AVERAGE(S44:U44)))) -> 3.59 | Z44: =R44/Y44-1 -> 0 | AA44: =R44-Y44 -> 0 | AB44: =R44=Y44 -> TRUE | AC44: 11-06-2026 | AD44: 3.19
A45: g27b053 | B45: r40f34s14 | C45: =MID(A45,2,2) -> 27 | D45: =_xlfn.XLOOKUP(C45,Folha2!A:A,Folha2!B:B) -> TAKE AWAY | E45: =MID(A45,5,3) -> 053 | F45: =MID(B45,5,2) -> 34 | G45: =MID(B45,8,2) -> 14 | H45: 01875834 | I45: TIRAS BRASEADAS VEGETAR. 175G | J45: G.GOURMET | K45: 7290109357829 | L45: E | M45: N | N45: N | O45: N | P45: N | Q45: 07 | R45: 3.59 | S45: 3.59 | Y45: =IF(OR(N45="O",O45="O"),IF(COUNT(V45:X45)>0,MIN(V45:X45),MIN(S45:U45)),IF(M45="O",MIN(S45:U45),IF(L45="E",IFERROR(MODE(S45:U45),MIN(S45:U45)),AVERAGE(S45:U45)))) -> 3.59 | Z45: =R45/Y45-1 -> 0 | AA45: =R45-Y45 -> 0 | AB45: =R45=Y45 -> TRUE | AC45: 11-06-2026 | AD45: 3.19
A46: g27b053 | B46: r40f34s14 | C46: =MID(A46,2,2) -> 27 | D46: =_xlfn.XLOOKUP(C46,Folha2!A:A,Folha2!B:B) -> TAKE AWAY | E46: =MID(A46,5,3) -> 053 | F46: =MID(B46,5,2) -> 34 | G46: =MID(B46,8,2) -> 14 | H46: 02119822 | I46: VEGGIE BALLS 200G | J46: G.GOURMET | K46: 8445291284692 | L46: E | M46: N | N46: N | O46: N | P46: N | Q46: 07 | R46: 3.59 | S46: 3.59 | Y46: =IF(OR(N46="O",O46="O"),IF(COUNT(V46:X46)>0,MIN(V46:X46),MIN(S46:U46)),IF(M46="O",MIN(S46:U46),IF(L46="E",IFERROR(MODE(S46:U46),MIN(S46:U46)),AVERAGE(S46:U46)))) -> 3.59 | Z46: =R46/Y46-1 -> 0 | AA46: =R46-Y46 -> 0 | AB46: =R46=Y46 -> TRUE | AC46: 11-06-2026 | AD46: 3.19
A47: g27b053 | B47: r40f34s14 | C47: =MID(A47,2,2) -> 27 | D47: =_xlfn.XLOOKUP(C47,Folha2!A:A,Folha2!B:B) -> TAKE AWAY | E47: =MID(A47,5,3) -> 053 | F47: =MID(B47,5,2) -> 34 | G47: =MID(B47,8,2) -> 14 | H47: 01875801 | I47: NUGGETS VEGETARIANOS 200G | J47: G.GOURMET | K47: 7613287424358 | L47: E | M47: N | N47: N | O47: N | P47: N | Q47: 07 | R47: 3.99 | S47: 3.99 | Y47: =IF(OR(N47="O",O47="O"),IF(COUNT(V47:X47)>0,MIN(V47:X47),MIN(S47:U47)),IF(M47="O",MIN(S47:U47),IF(L47="E",IFERROR(MODE(S47:U47),MIN(S47:U47)),AVERAGE(S47:U47)))) -> 3.99 | Z47: =R47/Y47-1 -> 0 | AA47: =R47-Y47 -> 0 | AB47: =R47=Y47 -> TRUE | AC47: 11-06-2026 | AD47: 3.59
A48: g27b053 | B48: r40f34s14 | C48: =MID(A48,2,2) -> 27 | D48: =_xlfn.XLOOKUP(C48,Folha2!A:A,Folha2!B:B) -> TAKE AWAY | E48: =MID(A48,5,3) -> 053 | F48: =MID(B48,5,2) -> 34 | G48: =MID(B48,8,2) -> 14 | H48: 01875812 | I48: ALMONDEGAS VEGETARIANAS 200G | J48: G.GOURMET | K48: 8445291849914 | L48: E | M48: N | N48: N | O48: N | P48: N | Q48: 07 | R48: 3.99 | S48: 3.99 | Y48: =IF(OR(N48="O",O48="O"),IF(COUNT(V48:X48)>0,MIN(V48:X48),MIN(S48:U48)),IF(M48="O",MIN(S48:U48),IF(L48="E",IFERROR(MODE(S48:U48),MIN(S48:U48)),AVERAGE(S48:U48)))) -> 3.99 | Z48: =R48/Y48-1 -> 0 | AA48: =R48-Y48 -> 0 | AB48: =R48=Y48 -> TRUE | AC48: 11-06-2026 | AD48: 3.59
A49: g27b053 | B49: r40f34s14 | C49: =MID(A49,2,2) -> 27 | D49: =_xlfn.XLOOKUP(C49,Folha2!A:A,Folha2!B:B) -> TAKE AWAY | E49: =MID(A49,5,3) -> 053 | F49: =MID(B49,5,2) -> 34 | G49: =MID(B49,8,2) -> 14 | H49: 01925036 | I49: TIRAS MARINADAS VEGAN 160G | J49: G.GOURMET | K49: 7613287503107 | L49: E | M49: N | N49: N | O49: N | P49: N | Q49: 07 | R49: 3.99 | S49: 3.99 | Y49: =IF(OR(N49="O",O49="O"),IF(COUNT(V49:X49)>0,MIN(V49:X49),MIN(S49:U49)),IF(M49="O",MIN(S49:U49),IF(L49="E",IFERROR(MODE(S49:U49),MIN(S49:U49)),AVERAGE(S49:U49)))) -> 3.99 | Z49: =R49/Y49-1 -> 0 | AA49: =R49-Y49 -> 0 | AB49: =R49=Y49 -> TRUE | AC49: 11-06-2026 | AD49: 3.59
A50: g27b053 | B50: r40f34s14 | C50: =MID(A50,2,2) -> 27 | D50: =_xlfn.XLOOKUP(C50,Folha2!A:A,Folha2!B:B) -> TAKE AWAY | E50: =MID(A50,5,3) -> 053 | F50: =MID(B50,5,2) -> 34 | G50: =MID(B50,8,2) -> 14 | H50: 01925040 | I50: FALAFEL VEGAN 190G | J50: G.GOURMET | K50: 8445291339842 | L50: E | M50: N | N50: N | O50: N | P50: N | Q50: 07 | R50: 3.99 | S50: 3.99 | Y50: =IF(OR(N50="O",O50="O"),IF(COUNT(V50:X50)>0,MIN(V50:X50),MIN(S50:U50)),IF(M50="O",MIN(S50:U50),IF(L50="E",IFERROR(MODE(S50:U50),MIN(S50:U50)),AVERAGE(S50:U50)))) -> 3.99 | Z50: =R50/Y50-1 -> 0 | AA50: =R50-Y50 -> 0 | AB50: =R50=Y50 -> TRUE | AC50: 11-06-2026 | AD50: 3.59
A51: g27b053 | B51: r40f34s14 | C51: =MID(A51,2,2) -> 27 | D51: =_xlfn.XLOOKUP(C51,Folha2!A:A,Folha2!B:B) -> TAKE AWAY | E51: =MID(A51,5,3) -> 053 | F51: =MID(B51,5,2) -> 34 | G51: =MID(B51,8,2) -> 14 | H51: 02172075 | I51: SCHNITZEL 180G | J51: G.GOURMET | K51: 8445291335646 | L51: E | M51: N | N51: N | O51: N | P51: N | Q51: 07 | R51: 3.99 | S51: 3.99 | Y51: =IF(OR(N51="O",O51="O"),IF(COUNT(V51:X51)>0,MIN(V51:X51),MIN(S51:U51)),IF(M51="O",MIN(S51:U51),IF(L51="E",IFERROR(MODE(S51:U51),MIN(S51:U51)),AVERAGE(S51:U51)))) -> 3.99 | Z51: =R51/Y51-1 -> 0 | AA51: =R51-Y51 -> 0 | AB51: =R51=Y51 -> TRUE | AC51: 11-06-2026 | AD51: 3.59
A52: g27b053 | B52: r40f34s14 | C52: =MID(A52,2,2) -> 27 | D52: =_xlfn.XLOOKUP(C52,Folha2!A:A,Folha2!B:B) -> TAKE AWAY | E52: =MID(A52,5,3) -> 053 | F52: =MID(B52,5,2) -> 34 | G52: =MID(B52,8,2) -> 14 | H52: 02157872 | I52: VUNA PROT VEG SABOR ATUM 175G | J52: G.GOURMET | K52: 8445291393981 | L52: E | M52: N | N52: N | O52: N | P52: N | Q52: 07 | R52: 6.55 | S52: 6.55 | U52: 5.89 | Y52: =IF(OR(N52="O",O52="O"),IF(COUNT(V52:X52)>0,MIN(V52:X52),MIN(S52:U52)),IF(M52="O",MIN(S52:U52),IF(L52="E",IFERROR(MODE(S52:U52),MIN(S52:U52)),AVERAGE(S52:U52)))) -> 5.89 | Z52: =R52/Y52-1 -> 0.11205433 | AA52: =R52-Y52 -> 0.66 | AB52: =R52=Y52 -> FALSE | AC52: 11-06-2026 | AD52: 5.59
A53: g27b053 | B53: r40f34s14 | C53: =MID(A53,2,2) -> 27 | D53: =_xlfn.XLOOKUP(C53,Folha2!A:A,Folha2!B:B) -> TAKE AWAY | E53: =MID(A53,5,3) -> 053 | F53: =MID(B53,5,2) -> 34 | G53: =MID(B53,8,2) -> 14 | H53: 01878624 | I53: ESCALOPE VEGETARIANO 160G | J53: NOBRE | K53: 5601119351943 | L53: E | M53: N | N53: N | O53: N | P53: N | Q53: 01 | R53: 4.39 | S53: 4.39 | Y53: =IF(OR(N53="O",O53="O"),IF(COUNT(V53:X53)>0,MIN(V53:X53),MIN(S53:U53)),IF(M53="O",MIN(S53:U53),IF(L53="E",IFERROR(MODE(S53:U53),MIN(S53:U53)),AVERAGE(S53:U53)))) -> 4.39 | Z53: =R53/Y53-1 -> 0 | AA53: =R53-Y53 -> 0 | AB53: =R53=Y53 -> TRUE | AC53: 02-07-2026 | AD53: 3.29
A54: g27b053 | B54: r40f34s14 | C54: =MID(A54,2,2) -> 27 | D54: =_xlfn.XLOOKUP(C54,Folha2!A:A,Folha2!B:B) -> TAKE AWAY | E54: =MID(A54,5,3) -> 053 | F54: =MID(B54,5,2) -> 34 | G54: =MID(B54,8,2) -> 14 | H54: 02135344 | I54: HAMBURGUER ESPINAFRES VEG 160G | J54: NOBRE | K54: 5601119308343 | L54: E | M54: N | N54: N | O54: N | P54: N | Q54: 01 | R54: 4.39 | S54: 4.39 | Y54: =IF(OR(N54="O",O54="O"),IF(COUNT(V54:X54)>0,MIN(V54:X54),MIN(S54:U54)),IF(M54="O",MIN(S54:U54),IF(L54="E",IFERROR(MODE(S54:U54),MIN(S54:U54)),AVERAGE(S54:U54)))) -> 4.39 | Z54: =R54/Y54-1 -> 0 | AA54: =R54-Y54 -> 0 | AB54: =R54=Y54 -> TRUE | AC54: 02-07-2026 | AD54: 3.29
A55: g27b053 | B55: r40f34s14 | C55: =MID(A55,2,2) -> 27 | D55: =_xlfn.XLOOKUP(C55,Folha2!A:A,Folha2!B:B) -> TAKE AWAY | E55: =MID(A55,5,3) -> 053 | F55: =MID(B55,5,2) -> 34 | G55: =MID(B55,8,2) -> 14 | H55: 01944052 | I55: PIZZA LEGUMES QUEIJO VEG 360G | J55: NOBRE | K55: 5601119371439 | L55: E | M55: N | N55: N | O55: N | P55: N | Q55: 03 | R55: 4.59 | S55: 4.59 | Y55: =IF(OR(N55="O",O55="O"),IF(COUNT(V55:X55)>0,MIN(V55:X55),MIN(S55:U55)),IF(M55="O",MIN(S55:U55),IF(L55="E",IFERROR(MODE(S55:U55),MIN(S55:U55)),AVERAGE(S55:U55)))) -> 4.59 | Z55: =R55/Y55-1 -> 0 | AA55: =R55-Y55 -> 0 | AB55: =R55=Y55 -> TRUE
A56: g27b053 | B56: r40f34s14 | C56: =MID(A56,2,2) -> 27 | D56: =_xlfn.XLOOKUP(C56,Folha2!A:A,Folha2!B:B) -> TAKE AWAY | E56: =MID(A56,5,3) -> 053 | F56: =MID(B56,5,2) -> 34 | G56: =MID(B56,8,2) -> 14 | H56: 01813361 | I56: LASANHA RICOTTA/ESPINAFRE 350G | J56: RANA | K56: 8001665127707 | L56: E | M56: N | N56: N | O56: N | P56: N | Q56: 01 | R56: 4.49 | S56: 4.49 | U56: 4.49 | Y56: =IF(OR(N56="O",O56="O"),IF(COUNT(V56:X56)>0,MIN(V56:X56),MIN(S56:U56)),IF(M56="O",MIN(S56:U56),IF(L56="E",IFERROR(MODE(S56:U56),MIN(S56:U56)),AVERAGE(S56:U56)))) -> 4.49 | Z56: =R56/Y56-1 -> 0 | AA56: =R56-Y56 -> 0 | AB56: =R56=Y56 -> TRUE | AC56: 23-07-2026 | AD56: 3.34
A57: g27b053 | B57: r40f34s18 | C57: =MID(A57,2,2) -> 27 | D57: =_xlfn.XLOOKUP(C57,Folha2!A:A,Folha2!B:B) -> TAKE AWAY | E57: =MID(A57,5,3) -> 053 | F57: =MID(B57,5,2) -> 34 | G57: =MID(B57,8,2) -> 18 | H57: 02056653 | I57: MINI PANQUECAS 250G | J57: PORSI | K57: 5604260331581 | L57: MP | M57: N | N57: N | O57: N | P57: N | Q57: 01 | R57: 1.99 | U57: 1.99 | Y57: =IF(OR(N57="O",O57="O"),IF(COUNT(V57:X57)>0,MIN(V57:X57),MIN(S57:U57)),IF(M57="O",MIN(S57:U57),IF(L57="E",IFERROR(MODE(S57:U57),MIN(S57:U57)),AVERAGE(S57:U57)))) -> 1.99 | Z57: =R57/Y57-1 -> 0 | AA57: =R57-Y57 -> 0 | AB57: =R57=Y57 -> TRUE | AC57: 02-07-2026 | AD57: 1.99
A58: g27b053 | B58: r40f34s20 | C58: =MID(A58,2,2) -> 27 | D58: =_xlfn.XLOOKUP(C58,Folha2!A:A,Folha2!B:B) -> TAKE AWAY | E58: =MID(A58,5,3) -> 053 | F58: =MID(B58,5,2) -> 34 | G58: =MID(B58,8,2) -> 20 | H58: 01856032 | I58: PREPARADO PATO DESFIADO 400G | J58: PORSI | K58: 5604260311644 | L58: MP | M58: N | N58: N | O58: N | P58: N | Q58: 01 | R58: 3.99 | S58: 4.19 | Y58: =IF(OR(N58="O",O58="O"),IF(COUNT(V58:X58)>0,MIN(V58:X58),MIN(S58:U58)),IF(M58="O",MIN(S58:U58),IF(L58="E",IFERROR(MODE(S58:U58),MIN(S58:U58)),AVERAGE(S58:U58)))) -> 4.19 | Z58: =R58/Y58-1 -> -0.047732697 | AA58: =R58-Y58 -> -0.2 | AB58: =R58=Y58 -> FALSE
A59: g27b053 | B59: r40f34s20 | C59: =MID(A59,2,2) -> 27 | D59: =_xlfn.XLOOKUP(C59,Folha2!A:A,Folha2!B:B) -> TAKE AWAY | E59: =MID(A59,5,3) -> 053 | F59: =MID(B59,5,2) -> 34 | G59: =MID(B59,8,2) -> 20 | H59: 02043566 | I59: TENTACULOS POLVO COZIDO 250G | J59: PORSI | K59: 5604260331109 | L59: MP | M59: N | N59: N | O59: N | P59: N | Q59: 01 | R59: 10.49 | S59: 10.49 | Y59: =IF(OR(N59="O",O59="O"),IF(COUNT(V59:X59)>0,MIN(V59:X59),MIN(S59:U59)),IF(M59="O",MIN(S59:U59),IF(L59="E",IFERROR(MODE(S59:U59),MIN(S59:U59)),AVERAGE(S59:U59)))) -> 10.49 | Z59: =R59/Y59-1 -> 0 | AA59: =R59-Y59 -> 0 | AB59: =R59=Y59 -> TRUE
A60: g27b053 | B60: r40f34s24 | C60: =MID(A60,2,2) -> 27 | D60: =_xlfn.XLOOKUP(C60,Folha2!A:A,Folha2!B:B) -> TAKE AWAY | E60: =MID(A60,5,3) -> 053 | F60: =MID(B60,5,2) -> 34 | G60: =MID(B60,8,2) -> 24 | H60: 01821742 | I60: MASSA FRESCA TAGLIATELLE 250G | J60: PORSI | K60: 5604260304851 | L60: MP | M60: N | N60: N | O60: N | P60: N | Q60: 01 | R60: 0.95 | S60: 0.95 | T60: 0.8 | Y60: =IF(OR(N60="O",O60="O"),IF(COUNT(V60:X60)>0,MIN(V60:X60),MIN(S60:U60)),IF(M60="O",MIN(S60:U60),IF(L60="E",IFERROR(MODE(S60:U60),MIN(S60:U60)),AVERAGE(S60:U60)))) -> 0.875 | Z60: =R60/Y60-1 -> 0.085714286 | AA60: =R60-Y60 -> 0.075 | AB60: =R60=Y60 -> FALSE
A61: g27b053 | B61: r40f34s24 | C61: =MID(A61,2,2) -> 27 | D61: =_xlfn.XLOOKUP(C61,Folha2!A:A,Folha2!B:B) -> TAKE AWAY | E61: =MID(A61,5,3) -> 053 | F61: =MID(B61,5,2) -> 34 | G61: =MID(B61,8,2) -> 24 | H61: 01821731 | I61: MASSA FRESCA LASANHA 250G | J61: PORSI | K61: 5604260304882 | L61: MP | M61: N | N61: N | O61: N | P61: N | Q61: 01 | R61: 1.09 | T61: 1.09 | Y61: =IF(OR(N61="O",O61="O"),IF(COUNT(V61:X61)>0,MIN(V61:X61),MIN(S61:U61)),IF(M61="O",MIN(S61:U61),IF(L61="E",IFERROR(MODE(S61:U61),MIN(S61:U61)),AVERAGE(S61:U61)))) -> 1.09 | Z61: =R61/Y61-1 -> 0 | AA61: =R61-Y61 -> 0 | AB61: =R61=Y61 -> TRUE
A62: g27b053 | B62: r40f34s24 | C62: =MID(A62,2,2) -> 27 | D62: =_xlfn.XLOOKUP(C62,Folha2!A:A,Folha2!B:B) -> TAKE AWAY | E62: =MID(A62,5,3) -> 053 | F62: =MID(B62,5,2) -> 34 | G62: =MID(B62,8,2) -> 24 | H62: 01821753 | I62: CAPPELLETTI CARNE&PRESUN. 250G | J62: PORSI | K62: 5604260307401 | L62: MP | M62: N | N62: N | O62: N | P62: N | Q62: 01 | R62: 1.79 | T62: 1.79 | Y62: =IF(OR(N62="O",O62="O"),IF(COUNT(V62:X62)>0,MIN(V62:X62),MIN(S62:U62)),IF(M62="O",MIN(S62:U62),IF(L62="E",IFERROR(MODE(S62:U62),MIN(S62:U62)),AVERAGE(S62:U62)))) -> 1.79 | Z62: =R62/Y62-1 -> 0 | AA62: =R62-Y62 -> 0 | AB62: =R62=Y62 -> TRUE
A63: g27b053 | B63: r40f34s24 | C63: =MID(A63,2,2) -> 27 | D63: =_xlfn.XLOOKUP(C63,Folha2!A:A,Folha2!B:B) -> TAKE AWAY | E63: =MID(A63,5,3) -> 053 | F63: =MID(B63,5,2) -> 34 | G63: =MID(B63,8,2) -> 24 | H63: 01821764 | I63: RAVIOLI 4 QUEIJOS 250G | J63: PORSI | K63: 5604260307388 | L63: MP | M63: N | N63: N | O63: N | P63: N | Q63: 01 | R63: 1.79 | T63: 1.79 | Y63: =IF(OR(N63="O",O63="O"),IF(COUNT(V63:X63)>0,MIN(V63:X63),MIN(S63:U63)),IF(M63="O",MIN(S63:U63),IF(L63="E",IFERROR(MODE(S63:U63),MIN(S63:U63)),AVERAGE(S63:U63)))) -> 1.79 | Z63: =R63/Y63-1 -> 0 | AA63: =R63-Y63 -> 0 | AB63: =R63=Y63 -> TRUE | AC63: 25-06-2026 | AD63: 1.79
A64: g27b053 | B64: r40f34s24 | C64: =MID(A64,2,2) -> 27 | D64: =_xlfn.XLOOKUP(C64,Folha2!A:A,Folha2!B:B) -> TAKE AWAY | E64: =MID(A64,5,3) -> 053 | F64: =MID(B64,5,2) -> 34 | G64: =MID(B64,8,2) -> 24 | H64: 01821775 | I64: RAVIOLI RICOTTA ESPINAFRE.250G | J64: PORSI | K64: 5604260307395 | L64: MP | M64: N | N64: N | O64: N | P64: N | Q64: 01 | R64: 1.79 | T64: 1.79 | Y64: =IF(OR(N64="O",O64="O"),IF(COUNT(V64:X64)>0,MIN(V64:X64),MIN(S64:U64)),IF(M64="O",MIN(S64:U64),IF(L64="E",IFERROR(MODE(S64:U64),MIN(S64:U64)),AVERAGE(S64:U64)))) -> 1.79 | Z64: =R64/Y64-1 -> 0 | AA64: =R64-Y64 -> 0 | AB64: =R64=Y64 -> TRUE | AC64: 25-06-2026 | AD64: 1.79
A65: g27b053 | B65: r40f34s24 | C65: =MID(A65,2,2) -> 27 | D65: =_xlfn.XLOOKUP(C65,Folha2!A:A,Folha2!B:B) -> TAKE AWAY | E65: =MID(A65,5,3) -> 053 | F65: =MID(B65,5,2) -> 34 | G65: =MID(B65,8,2) -> 24 | H65: 01980423 | I65: GNOCCHI 400G | J65: RANA | K65: 8001665734738 | L65: E | M65: N | N65: N | O65: N | P65: N | Q65: 01 | R65: 2.79 | S65: 2.79 | U65: 2.79 | Y65: =IF(OR(N65="O",O65="O"),IF(COUNT(V65:X65)>0,MIN(V65:X65),MIN(S65:U65)),IF(M65="O",MIN(S65:U65),IF(L65="E",IFERROR(MODE(S65:U65),MIN(S65:U65)),AVERAGE(S65:U65)))) -> 2.79 | Z65: =R65/Y65-1 -> 0 | AA65: =R65-Y65 -> 0 | AB65: =R65=Y65 -> TRUE | AC65: 25-06-2026 | AD65: 2.19
A66: g27b053 | B66: r40f34s24 | C66: =MID(A66,2,2) -> 27 | D66: =_xlfn.XLOOKUP(C66,Folha2!A:A,Folha2!B:B) -> TAKE AWAY | E66: =MID(A66,5,3) -> 053 | F66: =MID(B66,5,2) -> 34 | G66: =MID(B66,8,2) -> 24 | H66: 01560121 | I66: RAVIOLI DE FRANG.C/ALECRIM250G | J66: RANA | K66: 8001665717328 | L66: E | M66: N | N66: N | O66: N | P66: N | Q66: 01 | R66: 3.69 | S66: 3.69 | U66: 3.69 | Y66: =IF(OR(N66="O",O66="O"),IF(COUNT(V66:X66)>0,MIN(V66:X66),MIN(S66:U66)),IF(M66="O",MIN(S66:U66),IF(L66="E",IFERROR(MODE(S66:U66),MIN(S66:U66)),AVERAGE(S66:U66)))) -> 3.69 | Z66: =R66/Y66-1 -> 0 | AA66: =R66-Y66 -> 0 | AB66: =R66=Y66 -> TRUE | AC66: 11-06-2026 | AD66: 2.75
A67: g27b053 | B67: r40f34s24 | C67: =MID(A67,2,2) -> 27 | D67: =_xlfn.XLOOKUP(C67,Folha2!A:A,Folha2!B:B) -> TAKE AWAY | E67: =MID(A67,5,3) -> 053 | F67: =MID(B67,5,2) -> 34 | G67: =MID(B67,8,2) -> 24 | H67: 01907841 | I67: RAVIOLI ATUM E TOMATE 250G | J67: RANA | K67: 8001665717304 | L67: E | M67: N | N67: N | O67: N | P67: N | Q67: 01 | R67: 3.69 | S67: 3.69 | U67: 3.69 | Y67: =IF(OR(N67="O",O67="O"),IF(COUNT(V67:X67)>0,MIN(V67:X67),MIN(S67:U67)),IF(M67="O",MIN(S67:U67),IF(L67="E",IFERROR(MODE(S67:U67),MIN(S67:U67)),AVERAGE(S67:U67)))) -> 3.69 | Z67: =R67/Y67-1 -> 0 | AA67: =R67-Y67 -> 0 | AB67: =R67=Y67 -> TRUE | AC67: 11-06-2026 | AD67: 2.75
A68: g27b053 | B68: r40f34s24 | C68: =MID(A68,2,2) -> 27 | D68: =_xlfn.XLOOKUP(C68,Folha2!A:A,Folha2!B:B) -> TAKE AWAY | E68: =MID(A68,5,3) -> 053 | F68: =MID(B68,5,2) -> 34 | G68: =MID(B68,8,2) -> 24 | H68: 02110921 | I68: RAVIOLI BOLONHESA 250G | J68: RANA | K68: 8001665717281 | L68: E | M68: N | N68: N | O68: N | P68: N | Q68: 01 | R68: 3.69 | S68: 3.69 | U68: 3.69 | Y68: =IF(OR(N68="O",O68="O"),IF(COUNT(V68:X68)>0,MIN(V68:X68),MIN(S68:U68)),IF(M68="O",MIN(S68:U68),IF(L68="E",IFERROR(MODE(S68:U68),MIN(S68:U68)),AVERAGE(S68:U68)))) -> 3.69 | Z68: =R68/Y68-1 -> 0 | AA68: =R68-Y68 -> 0 | AB68: =R68=Y68 -> TRUE | AC68: 18-06-2026 | AD68: 2.75
A69: g27b053 | B69: r40f34s24 | C69: =MID(A69,2,2) -> 27 | D69: =_xlfn.XLOOKUP(C69,Folha2!A:A,Folha2!B:B) -> TAKE AWAY | E69: =MID(A69,5,3) -> 053 | F69: =MID(B69,5,2) -> 34 | G69: =MID(B69,8,2) -> 24 | H69: 02110932 | I69: RAV FAMBRE QJ 250G | J69: RANA | K69: 8001665717311 | L69: E | M69: N | N69: N | O69: N | P69: N | Q69: 01 | R69: 3.69 | S69: 3.69 | U69: 3.69 | Y69: =IF(OR(N69="O",O69="O"),IF(COUNT(V69:X69)>0,MIN(V69:X69),MIN(S69:U69)),IF(M69="O",MIN(S69:U69),IF(L69="E",IFERROR(MODE(S69:U69),MIN(S69:U69)),AVERAGE(S69:U69)))) -> 3.69 | Z69: =R69/Y69-1 -> 0 | AA69: =R69-Y69 -> 0 | AB69: =R69=Y69 -> TRUE | AC69: 02-07-2026 | AD69: 2.75
A70: g27b053 | B70: r40f34s24 | C70: =MID(A70,2,2) -> 27 | D70: =_xlfn.XLOOKUP(C70,Folha2!A:A,Folha2!B:B) -> TAKE AWAY | E70: =MID(A70,5,3) -> 053 | F70: =MID(B70,5,2) -> 34 | G70: =MID(B70,8,2) -> 24 | H70: 02110954 | I70: RAVIOLI 4 QUEIJOS 250G | J70: RANA | K70: 8001665717298 | L70: E | M70: N | N70: N | O70: N | P70: N | Q70: 01 | R70: 3.69 | S70: 3.69 | U70: 3.69 | Y70: =IF(OR(N70="O",O70="O"),IF(COUNT(V70:X70)>0,MIN(V70:X70),MIN(S70:U70)),IF(M70="O",MIN(S70:U70),IF(L70="E",IFERROR(MODE(S70:U70),MIN(S70:U70)),AVERAGE(S70:U70)))) -> 3.69 | Z70: =R70/Y70-1 -> 0 | AA70: =R70-Y70 -> 0 | AB70: =R70=Y70 -> TRUE | AC70: 18-06-2026 | AD70: 2.75
A71: g27b053 | B71: r40f34s24 | C71: =MID(A71,2,2) -> 27 | D71: =_xlfn.XLOOKUP(C71,Folha2!A:A,Folha2!B:B) -> TAKE AWAY | E71: =MID(A71,5,3) -> 053 | F71: =MID(B71,5,2) -> 34 | G71: =MID(B71,8,2) -> 24 | H71: 01979790 | I71: RAVIOLI COGUMELOS 250G | J71: RANA | K71: 8001665011617 | L71: E | M71: N | N71: N | O71: N | P71: N | Q71: 01 | R71: 3.99 | S71: 3.99 | U71: 3.99 | Y71: =IF(OR(N71="O",O71="O"),IF(COUNT(V71:X71)>0,MIN(V71:X71),MIN(S71:U71)),IF(M71="O",MIN(S71:U71),IF(L71="E",IFERROR(MODE(S71:U71),MIN(S71:U71)),AVERAGE(S71:U71)))) -> 3.99 | Z71: =R71/Y71-1 -> 0 | AA71: =R71-Y71 -> 0 | AB71: =R71=Y71 -> TRUE
A72: g27b053 | B72: r40f34s24 | C72: =MID(A72,2,2) -> 27 | D72: =_xlfn.XLOOKUP(C72,Folha2!A:A,Folha2!B:B) -> TAKE AWAY | E72: =MID(A72,5,3) -> 053 | F72: =MID(B72,5,2) -> 34 | G72: =MID(B72,8,2) -> 24 | H72: 02005294 | I72: RAV ABOBORA E CEB. CAR 250G | J72: RANA | K72: 8001665126090 | L72: E | M72: N | N72: N | O72: N | P72: N | Q72: 01 | R72: 3.99 | S72: 3.99 | U72: 3.99 | Y72: =IF(OR(N72="O",O72="O"),IF(COUNT(V72:X72)>0,MIN(V72:X72),MIN(S72:U72)),IF(M72="O",MIN(S72:U72),IF(L72="E",IFERROR(MODE(S72:U72),MIN(S72:U72)),AVERAGE(S72:U72)))) -> 3.99 | Z72: =R72/Y72-1 -> 0 | AA72: =R72-Y72 -> 0 | AB72: =R72=Y72 -> TRUE
A73: g27b053 | B73: r40f34s24 | C73: =MID(A73,2,2) -> 27 | D73: =_xlfn.XLOOKUP(C73,Folha2!A:A,Folha2!B:B) -> TAKE AWAY | E73: =MID(A73,5,3) -> 053 | F73: =MID(B73,5,2) -> 34 | G73: =MID(B73,8,2) -> 24 | H73: 02107762 | I73: RAV.TOMATE MOZ.250G | J73: RANA | K73: 8001665727341 | L73: E | M73: N | N73: N | O73: N | P73: N | Q73: 01 | R73: 3.99 | S73: 3.99 | Y73: =IF(OR(N73="O",O73="O"),IF(COUNT(V73:X73)>0,MIN(V73:X73),MIN(S73:U73)),IF(M73="O",MIN(S73:U73),IF(L73="E",IFERROR(MODE(S73:U73),MIN(S73:U73)),AVERAGE(S73:U73)))) -> 3.99 | Z73: =R73/Y73-1 -> 0 | AA73: =R73-Y73 -> 0 | AB73: =R73=Y73 -> TRUE
A74: g27b053 | B74: r40f34s24 | C74: =MID(A74,2,2) -> 27 | D74: =_xlfn.XLOOKUP(C74,Folha2!A:A,Folha2!B:B) -> TAKE AWAY | E74: =MID(A74,5,3) -> 053 | F74: =MID(B74,5,2) -> 34 | G74: =MID(B74,8,2) -> 24 | H74: 02110943 | I74: RAV RICOTA ESPINAFRES 250G | J74: RANA | K74: 8001665123815 | L74: E | M74: N | N74: N | O74: N | P74: N | Q74: 01 | R74: 3.99 | S74: 3.99 | U74: 3.99 | Y74: =IF(OR(N74="O",O74="O"),IF(COUNT(V74:X74)>0,MIN(V74:X74),MIN(S74:U74)),IF(M74="O",MIN(S74:U74),IF(L74="E",IFERROR(MODE(S74:U74),MIN(S74:U74)),AVERAGE(S74:U74)))) -> 3.99 | Z74: =R74/Y74-1 -> 0 | AA74: =R74-Y74 -> 0 | AB74: =R74=Y74 -> TRUE | AC74: 11-06-2026 | AD74: 2.99
A75: g27b053 | B75: r40f34s24 | C75: =MID(A75,2,2) -> 27 | D75: =_xlfn.XLOOKUP(C75,Folha2!A:A,Folha2!B:B) -> TAKE AWAY | E75: =MID(A75,5,3) -> 053 | F75: =MID(B75,5,2) -> 34 | G75: =MID(B75,8,2) -> 24 | H75: 01961174 | I75: RAVI. QJ CABRA CEBOLA CAR 250G | J75: RANA | K75: 8001665116275 | L75: E | M75: N | N75: N | O75: N | P75: N | Q75: 01 | R75: 4.19 | S75: 4.19 | Y75: =IF(OR(N75="O",O75="O"),IF(COUNT(V75:X75)>0,MIN(V75:X75),MIN(S75:U75)),IF(M75="O",MIN(S75:U75),IF(L75="E",IFERROR(MODE(S75:U75),MIN(S75:U75)),AVERAGE(S75:U75)))) -> 4.19 | Z75: =R75/Y75-1 -> 0 | AA75: =R75-Y75 -> 0 | AB75: =R75=Y75 -> TRUE
A76: g27b053 | B76: r40f34s24 | C76: =MID(A76,2,2) -> 27 | D76: =_xlfn.XLOOKUP(C76,Folha2!A:A,Folha2!B:B) -> TAKE AWAY | E76: =MID(A76,5,3) -> 053 | F76: =MID(B76,5,2) -> 34 | G76: =MID(B76,8,2) -> 24 | H76: 02005314 | I76: RAV TRUFAS BRANCA 250G | J76: RANA | K76: 8001665700900 | L76: E | M76: N | N76: N | O76: N | P76: N | Q76: 01 | R76: 4.19 | S76: 4.19 | Y76: =IF(OR(N76="O",O76="O"),IF(COUNT(V76:X76)>0,MIN(V76:X76),MIN(S76:U76)),IF(M76="O",MIN(S76:U76),IF(L76="E",IFERROR(MODE(S76:U76),MIN(S76:U76)),AVERAGE(S76:U76)))) -> 4.19 | Z76: =R76/Y76-1 -> 0 | AA76: =R76-Y76 -> 0 | AB76: =R76=Y76 -> TRUE
A77: g27b053 | B77: r40f34s24 | C77: =MID(A77,2,2) -> 27 | D77: =_xlfn.XLOOKUP(C77,Folha2!A:A,Folha2!B:B) -> TAKE AWAY | E77: =MID(A77,5,3) -> 053 | F77: =MID(B77,5,2) -> 34 | G77: =MID(B77,8,2) -> 24 | H77: 02172086 | I77: KIT SPAGHETTI CARBONARA 357G | J77: RANA | K77: 8001665731263 | L77: E | M77: N | N77: N | O77: N | P77: N | Q77: 01 | R77: 4.99 | S77: 4.99 | V77: 3.74 | Y77: =IF(OR(N77="O",O77="O"),IF(COUNT(V77:X77)>0,MIN(V77:X77),MIN(S77:U77)),IF(M77="O",MIN(S77:U77),IF(L77="E",IFERROR(MODE(S77:U77),MIN(S77:U77)),AVERAGE(S77:U77)))) -> 4.99 | Z77: =R77/Y77-1 -> 0 | AA77: =R77-Y77 -> 0 | AB77: =R77=Y77 -> TRUE
A78: g27b053 | B78: r40f34s24 | C78: =MID(A78,2,2) -> 27 | D78: =_xlfn.XLOOKUP(C78,Folha2!A:A,Folha2!B:B) -> TAKE AWAY | E78: =MID(A78,5,3) -> 053 | F78: =MID(B78,5,2) -> 34 | G78: =MID(B78,8,2) -> 24 | H78: 02172090 | I78: KIT PAPPARDELLE RAGU TOSC 357G | J78: RANA | K78: 8001665731270 | L78: E | M78: N | N78: N | O78: N | P78: N | Q78: 01 | R78: 4.99 | S78: 4.99 | V78: 3.74 | Y78: =IF(OR(N78="O",O78="O"),IF(COUNT(V78:X78)>0,MIN(V78:X78),MIN(S78:U78)),IF(M78="O",MIN(S78:U78),IF(L78="E",IFERROR(MODE(S78:U78),MIN(S78:U78)),AVERAGE(S78:U78)))) -> 4.99 | Z78: =R78/Y78-1 -> 0 | AA78: =R78-Y78 -> 0 | AB78: =R78=Y78 -> TRUE
A79: g27b053 | B79: r40f34s24 | C79: =MID(A79,2,2) -> 27 | D79: =_xlfn.XLOOKUP(C79,Folha2!A:A,Folha2!B:B) -> TAKE AWAY | E79: =MID(A79,5,3) -> 053 | F79: =MID(B79,5,2) -> 34 | G79: =MID(B79,8,2) -> 24 | H79: 02172110 | I79: KIT INDIANO BUTTER CHICK 351G | J79: RANA | K79: 8001665731300 | L79: E | M79: N | N79: N | O79: N | P79: N | Q79: 01 | R79: 4.99 | S79: 4.99 | V79: 3.74 | Y79: =IF(OR(N79="O",O79="O"),IF(COUNT(V79:X79)>0,MIN(V79:X79),MIN(S79:U79)),IF(M79="O",MIN(S79:U79),IF(L79="E",IFERROR(MODE(S79:U79),MIN(S79:U79)),AVERAGE(S79:U79)))) -> 4.99 | Z79: =R79/Y79-1 -> 0 | AA79: =R79-Y79 -> 0 | AB79: =R79=Y79 -> TRUE
A80: g27b053 | B80: r40f34s26 | C80: =MID(A80,2,2) -> 27 | D80: =_xlfn.XLOOKUP(C80,Folha2!A:A,Folha2!B:B) -> TAKE AWAY | E80: =MID(A80,5,3) -> 053 | F80: =MID(B80,5,2) -> 34 | G80: =MID(B80,8,2) -> 26 | H80: 01591162 | I80: MASSA FOLHADA 230G | J80: PASTA DIA | K80: 5600376210093 | L80: E | M80: N | N80: N | O80: N | P80: N | Q80: 01 | R80: 2.09 | S80: 2.09 | U80: 2.09 | Y80: =IF(OR(N80="O",O80="O"),IF(COUNT(V80:X80)>0,MIN(V80:X80),MIN(S80:U80)),IF(M80="O",MIN(S80:U80),IF(L80="E",IFERROR(MODE(S80:U80),MIN(S80:U80)),AVERAGE(S80:U80)))) -> 2.09 | Z80: =R80/Y80-1 -> 0 | AA80: =R80-Y80 -> 0 | AB80: =R80=Y80 -> TRUE | AC80: 25-06-2026 | AD80: 1.65
A81: g27b053 | B81: r40f34s26 | C81: =MID(A81,2,2) -> 27 | D81: =_xlfn.XLOOKUP(C81,Folha2!A:A,Folha2!B:B) -> TAKE AWAY | E81: =MID(A81,5,3) -> 053 | F81: =MID(B81,5,2) -> 34 | G81: =MID(B81,8,2) -> 26 | H81: 01591173 | I81: MASSA QUEBRADA 230G | J81: PASTA DIA | K81: 5600376210109 | L81: E | M81: N | N81: N | O81: N | P81: N | Q81: 01 | R81: 2.09 | S81: 2.09 | U81: 2.09 | Y81: =IF(OR(N81="O",O81="O"),IF(COUNT(V81:X81)>0,MIN(V81:X81),MIN(S81:U81)),IF(M81="O",MIN(S81:U81),IF(L81="E",IFERROR(MODE(S81:U81),MIN(S81:U81)),AVERAGE(S81:U81)))) -> 2.09 | Z81: =R81/Y81-1 -> 0 | AA81: =R81-Y81 -> 0 | AB81: =R81=Y81 -> TRUE | AC81: 25-06-2026 | AD81: 1.65
A82: g27b053 | B82: r40f34s26 | C82: =MID(A82,2,2) -> 27 | D82: =_xlfn.XLOOKUP(C82,Folha2!A:A,Folha2!B:B) -> TAKE AWAY | E82: =MID(A82,5,3) -> 053 | F82: =MID(B82,5,2) -> 34 | G82: =MID(B82,8,2) -> 26 | H82: 01591252 | I82: FOLHAS LASANHA 250G | J82: PASTA DIA | K82: 5600376210192 | L82: E | M82: N | N82: N | O82: N | P82: N | Q82: 01 | R82: 2.38 | S82: 2.39 | Y82: =IF(OR(N82="O",O82="O"),IF(COUNT(V82:X82)>0,MIN(V82:X82),MIN(S82:U82)),IF(M82="O",MIN(S82:U82),IF(L82="E",IFERROR(MODE(S82:U82),MIN(S82:U82)),AVERAGE(S82:U82)))) -> 2.39 | Z82: =R82/Y82-1 -> -0.0041841004 | AA82: =R82-Y82 -> -0.01 | AB82: =R82=Y82 -> FALSE | AC82: 23-07-2026 | AD82: 1.89
A83: g27b053 | B83: r40f34s26 | C83: =MID(A83,2,2) -> 27 | D83: =_xlfn.XLOOKUP(C83,Folha2!A:A,Folha2!B:B) -> TAKE AWAY | E83: =MID(A83,5,3) -> 053 | F83: =MID(B83,5,2) -> 34 | G83: =MID(B83,8,2) -> 26 | H83: 01591195 | I83: MASSA PIZZA 230G | J83: PASTA DIA | K83: 5600376210079 | L83: E | M83: N | N83: N | O83: N | P83: N | Q83: 01 | R83: 2.39 | S83: 2.39 | U83: 2.39 | Y83: =IF(OR(N83="O",O83="O"),IF(COUNT(V83:X83)>0,MIN(V83:X83),MIN(S83:U83)),IF(M83="O",MIN(S83:U83),IF(L83="E",IFERROR(MODE(S83:U83),MIN(S83:U83)),AVERAGE(S83:U83)))) -> 2.39 | Z83: =R83/Y83-1 -> 0 | AA83: =R83-Y83 -> 0 | AB83: =R83=Y83 -> TRUE | AC83: 09-07-2026 | AD83: 1.89
A84: g27b053 | B84: r40f34s26 | C84: =MID(A84,2,2) -> 27 | D84: =_xlfn.XLOOKUP(C84,Folha2!A:A,Folha2!B:B) -> TAKE AWAY | E84: =MID(A84,5,3) -> 053 | F84: =MID(B84,5,2) -> 34 | G84: =MID(B84,8,2) -> 26 | H84: 01591184 | I84: QUAD.MASSA FOLHADA 300G | J84: PASTA DIA | K84: 5600376210116 | L84: E | M84: N | N84: N | O84: N | P84: N | Q84: 01 | R84: 2.79 | S84: 2.79 | U84: 2.79 | Y84: =IF(OR(N84="O",O84="O"),IF(COUNT(V84:X84)>0,MIN(V84:X84),MIN(S84:U84)),IF(M84="O",MIN(S84:U84),IF(L84="E",IFERROR(MODE(S84:U84),MIN(S84:U84)),AVERAGE(S84:U84)))) -> 2.79 | Z84: =R84/Y84-1 -> 0 | AA84: =R84-Y84 -> 0 | AB84: =R84=Y84 -> TRUE | AC84: 30-07-2026 | AD84: 2.19
A85: g27b053 | B85: r40f34s26 | C85: =MID(A85,2,2) -> 27 | D85: =_xlfn.XLOOKUP(C85,Folha2!A:A,Folha2!B:B) -> TAKE AWAY | E85: =MID(A85,5,3) -> 053 | F85: =MID(B85,5,2) -> 34 | G85: =MID(B85,8,2) -> 26 | H85: 01839123 | I85: MASSA TENRA 300G | J85: PASTA DIA | K85: 5600376210406 | L85: E | M85: N | N85: N | O85: N | P85: N | Q85: 01 | R85: 2.99 | S85: 2.99 | U85: 2.99 | Y85: =IF(OR(N85="O",O85="O"),IF(COUNT(V85:X85)>0,MIN(V85:X85),MIN(S85:U85)),IF(M85="O",MIN(S85:U85),IF(L85="E",IFERROR(MODE(S85:U85),MIN(S85:U85)),AVERAGE(S85:U85)))) -> 2.99 | Z85: =R85/Y85-1 -> 0 | AA85: =R85-Y85 -> 0 | AB85: =R85=Y85 -> TRUE | AC85: 23-07-2026 | AD85: 2.39
A86: g27b053 | B86: r40f34s26 | C86: =MID(A86,2,2) -> 27 | D86: =_xlfn.XLOOKUP(C86,Folha2!A:A,Folha2!B:B) -> TAKE AWAY | E86: =MID(A86,5,3) -> 053 | F86: =MID(B86,5,2) -> 34 | G86: =MID(B86,8,2) -> 26 | H86: 01591226 | I86: MASSA QUEBRADA S/GLUTEN 230G | J86: PASTA DIA | K86: 5600376210314 | L86: E | M86: N | N86: N | O86: N | P86: N | Q86: 01 | R86: 3.28 | S86: 3.29 | Y86: =IF(OR(N86="O",O86="O"),IF(COUNT(V86:X86)>0,MIN(V86:X86),MIN(S86:U86)),IF(M86="O",MIN(S86:U86),IF(L86="E",IFERROR(MODE(S86:U86),MIN(S86:U86)),AVERAGE(S86:U86)))) -> 3.29 | Z86: =R86/Y86-1 -> -0.0030395137 | AA86: =R86-Y86 -> -0.01 | AB86: =R86=Y86 -> FALSE | AC86: 25-06-2026 | AD86: 2.59
A87: g27b053 | B87: r40f34s26 | C87: =MID(A87,2,2) -> 27 | D87: =_xlfn.XLOOKUP(C87,Folha2!A:A,Folha2!B:B) -> TAKE AWAY | E87: =MID(A87,5,3) -> 053 | F87: =MID(B87,5,2) -> 34 | G87: =MID(B87,8,2) -> 26 | H87: 01591215 | I87: MASSA FOLHADA S/GLUTEN 280G | J87: PASTA DIA | K87: 5600376210291 | L87: E | M87: N | N87: N | O87: N | P87: N | Q87: 01 | R87: 3.28 | S87: 3.29 | U87: 3.28 | Y87: =IF(OR(N87="O",O87="O"),IF(COUNT(V87:X87)>0,MIN(V87:X87),MIN(S87:U87)),IF(M87="O",MIN(S87:U87),IF(L87="E",IFERROR(MODE(S87:U87),MIN(S87:U87)),AVERAGE(S87:U87)))) -> 3.28 | Z87: =R87/Y87-1 -> 0 | AA87: =R87-Y87 -> 0 | AB87: =R87=Y87 -> TRUE | AC87: 23-07-2026 | AD87: 2.59
A88: g27b053 | B88: r40f34s26 | C88: =MID(A88,2,2) -> 27 | D88: =_xlfn.XLOOKUP(C88,Folha2!A:A,Folha2!B:B) -> TAKE AWAY | E88: =MID(A88,5,3) -> 053 | F88: =MID(B88,5,2) -> 34 | G88: =MID(B88,8,2) -> 26 | H88: 01981810 | I88: MASSA FOLHADA RETANGULAR 250G | J88: PORSI | K88: 5604260328284 | L88: MP | M88: O | N88: N | O88: N | P88: O | Q88: 01 | R88: 0.9 | S88: 0.9 | T88: 0.9 | Y88: =IF(OR(N88="O",O88="O"),IF(COUNT(V88:X88)>0,MIN(V88:X88),MIN(S88:U88)),IF(M88="O",MIN(S88:U88),IF(L88="E",IFERROR(MODE(S88:U88),MIN(S88:U88)),AVERAGE(S88:U88)))) -> 0.9 | Z88: =R88/Y88-1 -> 0 | AA88: =R88-Y88 -> 0 | AB88: =R88=Y88 -> TRUE
A89: g27b053 | B89: r40f34s26 | C89: =MID(A89,2,2) -> 27 | D89: =_xlfn.XLOOKUP(C89,Folha2!A:A,Folha2!B:B) -> TAKE AWAY | E89: =MID(A89,5,3) -> 053 | F89: =MID(B89,5,2) -> 34 | G89: =MID(B89,8,2) -> 26 | H89: 01984925 | I89: BASE P/ PIZZA C/AZEITE 230G | J89: PORSI | K89: 5604260326815 | L89: MP | M89: N | N89: N | O89: N | P89: N | Q89: 01 | R89: 0.99 | S89: 0.81 | U89: 0.99 | Y89: =IF(OR(N89="O",O89="O"),IF(COUNT(V89:X89)>0,MIN(V89:X89),MIN(S89:U89)),IF(M89="O",MIN(S89:U89),IF(L89="E",IFERROR(MODE(S89:U89),MIN(S89:U89)),AVERAGE(S89:U89)))) -> 0.9 | Z89: =R89/Y89-1 -> 0.1 | AA89: =R89-Y89 -> 0.09 | AB89: =R89=Y89 -> FALSE
A90: g27b053 | B90: r40f34s26 | C90: =MID(A90,2,2) -> 27 | D90: =_xlfn.XLOOKUP(C90,Folha2!A:A,Folha2!B:B) -> TAKE AWAY | E90: =MID(A90,5,3) -> 053 | F90: =MID(B90,5,2) -> 34 | G90: =MID(B90,8,2) -> 26 | H90: 00681506 | I90: MASSA FOLHADA MARGARINA 230G | J90: PORSI | K90: 5604260297023 | L90: MP | M90: O | N90: N | O90: N | P90: O | Q90: 01 | R90: 0.99 | S90: 0.95 | T90: 0.95 | U90: 0.95 | Y90: =IF(OR(N90="O",O90="O"),IF(COUNT(V90:X90)>0,MIN(V90:X90),MIN(S90:U90)),IF(M90="O",MIN(S90:U90),IF(L90="E",IFERROR(MODE(S90:U90),MIN(S90:U90)),AVERAGE(S90:U90)))) -> 0.95 | Z90: =R90/Y90-1 -> 0.042105263 | AA90: =R90-Y90 -> 0.04 | AB90: =R90=Y90 -> FALSE
A91: g27b053 | B91: r40f34s26 | C91: =MID(A91,2,2) -> 27 | D91: =_xlfn.XLOOKUP(C91,Folha2!A:A,Folha2!B:B) -> TAKE AWAY | E91: =MID(A91,5,3) -> 053 | F91: =MID(B91,5,2) -> 34 | G91: =MID(B91,8,2) -> 26 | H91: 00681510 | I91: MASSA QUEBRADA MARGARINA 230G | J91: PORSI | K91: 5604260297030 | L91: MP | M91: O | N91: N | O91: N | P91: O | Q91: 01 | R91: 0.99 | S91: 0.99 | T91: 0.95 | Y91: =IF(OR(N91="O",O91="O"),IF(COUNT(V91:X91)>0,MIN(V91:X91),MIN(S91:U91)),IF(M91="O",MIN(S91:U91),IF(L91="E",IFERROR(MODE(S91:U91),MIN(S91:U91)),AVERAGE(S91:U91)))) -> 0.95 | Z91: =R91/Y91-1 -> 0.042105263 | AA91: =R91-Y91 -> 0.04 | AB91: =R91=Y91 -> FALSE
A92: g27b053 | B92: r40f34s26 | C92: =MID(A92,2,2) -> 27 | D92: =_xlfn.XLOOKUP(C92,Folha2!A:A,Folha2!B:B) -> TAKE AWAY | E92: =MID(A92,5,3) -> 053 | F92: =MID(B92,5,2) -> 34 | G92: =MID(B92,8,2) -> 26 | H92: 02130956 | I92: MASSA FILO 250G | J92: PORSI | K92: 5604260338290 | L92: MP | M92: N | N92: N | O92: N | P92: N | Q92: 01 | R92: 1.99 | S92: 1.99 | U92: 1.99 | Y92: =IF(OR(N92="O",O92="O"),IF(COUNT(V92:X92)>0,MIN(V92:X92),MIN(S92:U92)),IF(M92="O",MIN(S92:U92),IF(L92="E",IFERROR(MODE(S92:U92),MIN(S92:U92)),AVERAGE(S92:U92)))) -> 1.99 | Z92: =R92/Y92-1 -> 0 | AA92: =R92-Y92 -> 0 | AB92: =R92=Y92 -> TRUE
A93: g27b053 | B93: r40f34s26 | C93: =MID(A93,2,2) -> 27 | D93: =_xlfn.XLOOKUP(C93,Folha2!A:A,Folha2!B:B) -> TAKE AWAY | E93: =MID(A93,5,3) -> 053 | F93: =MID(B93,5,2) -> 34 | G93: =MID(B93,8,2) -> 26 | H93: 01560165 | I93: FOLHAS PARA LASANHA 250G | J93: RANA | K93: 8001665722605 | L93: E | M93: N | N93: N | O93: N | P93: N | Q93: 01 | R93: 2.79 | S93: 2.79 | U93: 2.79 | Y93: =IF(OR(N93="O",O93="O"),IF(COUNT(V93:X93)>0,MIN(V93:X93),MIN(S93:U93)),IF(M93="O",MIN(S93:U93),IF(L93="E",IFERROR(MODE(S93:U93),MIN(S93:U93)),AVERAGE(S93:U93)))) -> 2.79 | Z93: =R93/Y93-1 -> 0 | AA93: =R93-Y93 -> 0 | AB93: =R93=Y93 -> TRUE
A94: g37b065 | B94: r40f40s06 | C94: =MID(A94,2,2) -> 37 | D94: =_xlfn.XLOOKUP(C94,Folha2!A:A,Folha2!B:B) -> BVP | E94: =MID(A94,5,3) -> 065 | F94: =MID(B94,5,2) -> 40 | G94: =MID(B94,8,2) -> 06 | H94: 01568844 | I94: CROISSANT FOLHADO 50G | J94: PORSI | K94: 2696603000004 | L94: MP | M94: O | N94: N | O94: N | P94: O | Q94: 01 | R94: 0.45 | S94: 0.75 | Y94: =IF(OR(N94="O",O94="O"),IF(COUNT(V94:X94)>0,MIN(V94:X94),MIN(S94:U94)),IF(M94="O",MIN(S94:U94),IF(L94="E",IFERROR(MODE(S94:U94),MIN(S94:U94)),AVERAGE(S94:U94)))) -> 0.75 | Z94: =R94/Y94-1 -> -0.4 | AA94: =R94-Y94 -> -0.3 | AB94: =R94=Y94 -> FALSE
A95: g37b065 | B95: r40f40s06 | C95: =MID(A95,2,2) -> 37 | D95: =_xlfn.XLOOKUP(C95,Folha2!A:A,Folha2!B:B) -> BVP | E95: =MID(A95,5,3) -> 065 | F95: =MID(B95,5,2) -> 40 | G95: =MID(B95,8,2) -> 06 | H95: 00600372 | I95: QUEQUE 55G | J95: PORSI | K95: 2696304000006 | L95: MP | M95: N | N95: N | O95: N | P95: N | Q95: 01 | R95: 0.69 | S95: 1.58 | U95: 0.69 | Y95: =IF(OR(N95="O",O95="O"),IF(COUNT(V95:X95)>0,MIN(V95:X95),MIN(S95:U95)),IF(M95="O",MIN(S95:U95),IF(L95="E",IFERROR(MODE(S95:U95),MIN(S95:U95)),AVERAGE(S95:U95)))) -> 1.135 | Z95: =R95/Y95-1 -> -0.39207048 | AA95: =R95-Y95 -> -0.445 | AB95: =R95=Y95 -> FALSE
A96: g37b065 | B96: r40f40s06 | C96: =MID(A96,2,2) -> 37 | D96: =_xlfn.XLOOKUP(C96,Folha2!A:A,Folha2!B:B) -> BVP | E96: =MID(A96,5,3) -> 065 | F96: =MID(B96,5,2) -> 40 | G96: =MID(B96,8,2) -> 06 | H96: 00600313 | I96: BOLO ARROZ 70G | J96: PORSI | K96: 2696303000007 | L96: MP | M96: N | N96: N | O96: N | P96: N | Q96: 01 | R96: 0.69 | S96: 1.7 | U96: 0.81 | Y96: =IF(OR(N96="O",O96="O"),IF(COUNT(V96:X96)>0,MIN(V96:X96),MIN(S96:U96)),IF(M96="O",MIN(S96:U96),IF(L96="E",IFERROR(MODE(S96:U96),MIN(S96:U96)),AVERAGE(S96:U96)))) -> 1.255 | Z96: =R96/Y96-1 -> -0.4501992 | AA96: =R96-Y96 -> -0.565 | AB96: =R96=Y96 -> FALSE
A97: g37b065 | B97: r40f40s06 | C97: =MID(A97,2,2) -> 37 | D97: =_xlfn.XLOOKUP(C97,Folha2!A:A,Folha2!B:B) -> BVP | E97: =MID(A97,5,3) -> 065 | F97: =MID(B97,5,2) -> 40 | G97: =MID(B97,8,2) -> 06 | H97: 01907804 | I97: FOLHADO CHOC MANT PRE-CZ 60G | J97: PORSI | K97: 2696168000006 | L97: MP | M97: O | N97: N | O97: N | P97: O | Q97: 01 | R97: 0.77 | S97: 1.7 | Y97: =IF(OR(N97="O",O97="O"),IF(COUNT(V97:X97)>0,MIN(V97:X97),MIN(S97:U97)),IF(M97="O",MIN(S97:U97),IF(L97="E",IFERROR(MODE(S97:U97),MIN(S97:U97)),AVERAGE(S97:U97)))) -> 1.7 | Z97: =R97/Y97-1 -> -0.54705882 | AA97: =R97-Y97 -> -0.93 | AB97: =R97=Y97 -> FALSE | AC97: 11-06-2026 | AD97: 0.65
A98: g37b065 | B98: r40f40s06 | C98: =MID(A98,2,2) -> 37 | D98: =_xlfn.XLOOKUP(C98,Folha2!A:A,Folha2!B:B) -> BVP | E98: =MID(A98,5,3) -> 065 | F98: =MID(B98,5,2) -> 40 | G98: =MID(B98,8,2) -> 06 | H98: 01568855 | I98: NAPOLITANA DE CHOCOLATE 60G | J98: PORSI | K98: 2696604000003 | L98: MP | M98: O | N98: N | O98: N | P98: O | Q98: 01 | R98: 0.77 | S98: 1.98 | Y98: =IF(OR(N98="O",O98="O"),IF(COUNT(V98:X98)>0,MIN(V98:X98),MIN(S98:U98)),IF(M98="O",MIN(S98:U98),IF(L98="E",IFERROR(MODE(S98:U98),MIN(S98:U98)),AVERAGE(S98:U98)))) -> 1.98 | Z98: =R98/Y98-1 -> -0.61111111 | AA98: =R98-Y98 -> -1.21 | AB98: =R98=Y98 -> FALSE
A99: g37b065 | B99: r40f40s06 | C99: =MID(A99,2,2) -> 37 | D99: =_xlfn.XLOOKUP(C99,Folha2!A:A,Folha2!B:B) -> BVP | E99: =MID(A99,5,3) -> 065 | F99: =MID(B99,5,2) -> 40 | G99: =MID(B99,8,2) -> 06 | H99: 00968511 | I99: BOLA BERLIM CREME TRAD.100G | J99: PORSI | K99: 2696309000001 | L99: MP | M99: N | N99: N | O99: N | P99: N | Q99: 01 | R99: 0.89 | S99: 0.95 | U99: 0.89 | Y99: =IF(OR(N99="O",O99="O"),IF(COUNT(V99:X99)>0,MIN(V99:X99),MIN(S99:U99)),IF(M99="O",MIN(S99:U99),IF(L99="E",IFERROR(MODE(S99:U99),MIN(S99:U99)),AVERAGE(S99:U99)))) -> 0.92 | Z99: =R99/Y99-1 -> -0.032608696 | AA99: =R99-Y99 -> -0.03 | AB99: =R99=Y99 -> FALSE
A100: g37b065 | B100: r40f40s06 | C100: =MID(A100,2,2) -> 37 | D100: =_xlfn.XLOOKUP(C100,Folha2!A:A,Folha2!B:B) -> BVP | E100: =MID(A100,5,3) -> 065 | F100: =MID(B100,5,2) -> 40 | G100: =MID(B100,8,2) -> 06 | H100: 00105313 | I100: FOLHADO MACA 100G | J100: PORSI | K100: 2696106000006 | L100: MP | M100: O | N100: N | O100: N | P100: O | Q100: 01 | R100: 0.89 | S100: 1.5 | Y100: =IF(OR(N100="O",O100="O"),IF(COUNT(V100:X100)>0,MIN(V100:X100),MIN(S100:U100)),IF(M100="O",MIN(S100:U100),IF(L100="E",IFERROR(MODE(S100:U100),MIN(S100:U100)),AVERAGE(S100:U100)))) -> 1.5 | Z100: =R100/Y100-1 -> -0.40666667 | AA100: =R100-Y100 -> -0.61 | AB100: =R100=Y100 -> FALSE | AC100: 25-06-2026 | AD100: 0.79
A101: g37b065 | B101: r40f40s06 | C101: =MID(A101,2,2) -> 37 | D101: =_xlfn.XLOOKUP(C101,Folha2!A:A,Folha2!B:B) -> BVP | E101: =MID(A101,5,3) -> 065 | F101: =MID(B101,5,2) -> 40 | G101: =MID(B101,8,2) -> 06 | H101: 00452423 | I101: BOLA DE BERLIM CHOCOLATE 85G | J101: PORSI | K101: 2696305000005 | L101: MP | M101: N | N101: N | O101: N | P101: N | Q101: 01 | R101: 0.99 | S101: 0.95 | Y101: =IF(OR(N101="O",O101="O"),IF(COUNT(V101:X101)>0,MIN(V101:X101),MIN(S101:U101)),IF(M101="O",MIN(S101:U101),IF(L101="E",IFERROR(MODE(S101:U101),MIN(S101:U101)),AVERAGE(S101:U101)))) -> 0.95 | Z101: =R101/Y101-1 -> 0.042105263 | AA101: =R101-Y101 -> 0.04 | AB101: =R101=Y101 -> FALSE
...

Sheet Folha2
A1: Grp | B1: GRUPO
A2: 27 | B2: TAKE AWAY
A3: 37 | B3: BVP
A4: 38 | B4: CARNES E AVES
A5: 41 | B5: MAR
A6: 42 | B6: FRUTAS E LEGUMES
A7: 43 | B7: FRESCOS LACTEOS
A8: 44 | B8: FRESCOS NAO LACTEOS
A9: 45 | B9: DPH
A10: 46 | B10: MERCEARIA DOCE
A11: 47 | B11: MERCEARIA SALGADA
A12: 48 | B12: BEBIDAS
... A15: 51 | B15: TEXTIL
